[
  {
    "reviewRateId": 14853657560358,
    "reviewType": "PRODUCT_REVIEW",
    "buyerId": 764872,
    "buyerName": "saba A.",
    "buyerEmail": null,
    "realBuyerName": null,
    "isAnonymous": false,
    "tradeOrderId": null,
    "source": null,
    "clientType": "androidApp",
    "rating": 4,
    "originalRating": null,
    "reviewTitle": null,
    "reviewContent": "very nice dipers in this price..but absorption boht hi km hai plz do something with absorption capacity yeh 2 ghnty main hi leak ho jata hai... overall quality is good except for the capasity",
    "reviewTime": "03 Apr 2021",
    "zonedReviewTime": null,
    "likeCount": 0,
    "likeText": null,
    "isMeLike": null,
    "helpful": true,
    "rejected": false,
    "rejectionReason": null,
    "resubmissionTooltip": null,
    "resubmissionMessage": null,
    "qcReasonId": null,
    "qcDate": null,
    "isPurchased": true,
    "isGuest": false,
    "sellerId": 6005009103200,
    "sellerName": null,
    "boughtDate": "10 Mar 2021",
    "zonedBoughtDate": null,
    "reviewStatus": "approved",
    "qcTag": null,
    "qcScore": null,
    "isQced": false,
    "itemId": 171160358,
    "itemPic": "https://static-01.daraz.pk/p/a769833298a7eabb9b49689c3dadb286.jpg",
    "itemTitle": "BEBEM - Pack of 3 Baby diapers - Jumbo economy pack - Size 6 XXL - 44 Pcs ( 16+ kg ).",
    "itemUrl": "https://www.daraz.pk/bebem-pack-of-3-baby-diapers-jumbo-economy-pack-size-6-xxl-44-pcs-16-kg-i171160358-s1341700713.html",
    "originPrice": null,
    "salesPrice": null,
    "promotion": null,
    "skuInfo": "Size Diaper:XXL Size (14-25kg), Diaper Pack Size:44",
    "tags": null,
    "skuId": "1341700713",
    "configSku": "171160358_PK",
    "lastReviewer": "Sahani, KajolSahani, Kajol",
    "isReportable": 0,
    "reportStatus": null,
    "reportDate": null,
    "reportTimes": 0,
    "upVotes": 0,
    "downVotes": 0,
    "isExternal": 0,
    "replies": [],
    "canEdit": true,
    "images": [
      {
        "title": "",
        "url": "https://sg-test-11.slatic.net/other/roc/da351e647aeb88292452d986288ddfb3.jpg",
        "sort": 1,
        "uploadTime": 1617438553861,
        "legal": true,
        "status": "approved",
        "checkedByPeople": false,
        "width": 744,
        "height": 992,
        "size": 679310
      },
      {
        "title": "",
        "url": "https://sg-test-11.slatic.net/other/roc/114fc0595277a2816ab97b57d920b2a8.jpg",
        "sort": 2,
        "uploadTime": 1617438553861,
        "legal": true,
        "status": "approved",
        "checkedByPeople": false,
        "width": 744,
        "height": 992,
        "size": 467669
      },
      {
        "title": "",
        "url": "https://sg-test-11.slatic.net/other/roc/e5ebbb1d6c0c3608a5ff20881428b6e0.jpg",
        "sort": 3,
        "uploadTime": 1617438553861,
        "legal": true,
        "status": "approved",
        "checkedByPeople": false,
        "width": 744,
        "height": 992,
        "size": 621289
      }
    ],
    "imageQCStatus": "approved",
    "submitInfo": {
      "os": "ios",
      "source": "myreview",
      "terminal": "weex",
      "network": "WIFI"
    },
    "imageHost": "//sg-live.slatic.net",
    "showUploader": true,
    "showVideoUploader": false,
    "relevanceScore": 62.5,
    "isCompleted": 1,
    "videoId": null,
    "isVideoReady": null,
    "videoCoverUrl": null,
    "avatar": null,
    "canDownloadImage": null,
    "targetId": 171160358,
    "targetType": "item"
  },
  {
    "reviewRateId": 10402649860358,
    "reviewType": "PRODUCT_REVIEW",
    "buyerId": 600025221556,
    "buyerName": "mrs U.",
    "buyerEmail": null,
    "realBuyerName": null,
    "isAnonymous": false,
    "tradeOrderId": null,
    "source": null,
    "clientType": "androidApp",
    "rating": 5,
    "originalRating": null,
    "reviewTitle": null,
    "reviewContent": "i am totally satisfied from daraz. always recieve original dypers. quick service. delivery services are excellent. great job. best prices best quality . hats off.",
    "reviewTime": "03 Oct 2020",
    "zonedReviewTime": null,
    "likeCount": 0,
    "likeText": null,
    "isMeLike": null,
    "helpful": true,
    "rejected": false,
    "rejectionReason": null,
    "resubmissionTooltip": null,
    "resubmissionMessage": null,
    "qcReasonId": null,
    "qcDate": null,
    "isPurchased": true,
    "isGuest": false,
    "sellerId": 6005009103200,
    "sellerName": null,
    "boughtDate": "29 Sep 2020",
    "zonedBoughtDate": null,
    "reviewStatus": "approved",
    "qcTag": null,
    "qcScore": null,
    "isQced": false,
    "itemId": 171160358,
    "itemPic": "https://static-01.daraz.pk/p/6a6462c3a4cffb8b1cac5ea529f7dce4.jpg",
    "itemTitle": "BEBEM - Pack of 3 Baby diapers - Jumbo economy pack - Size 6 XXL - 44 Pcs ( 16+ kg ).",
    "itemUrl": "https://www.daraz.pk/bebem-pack-of-3-baby-diapers-jumbo-economy-pack-size-6-xxl-44-pcs-16-kg-i171160358-s1341700713.html",
    "originPrice": null,
    "salesPrice": null,
    "promotion": null,
    "skuInfo": "Size Diaper:XXL Size (14-25kg), Diaper Pack Size:44",
    "tags": null,
    "skuId": "1341700713",
    "configSku": "171160358_PK",
    "lastReviewer": "Khan, AyeshaKhan, Ayesha",
    "isReportable": 0,
    "reportStatus": null,
    "reportDate": null,
    "reportTimes": 0,
    "upVotes": 0,
    "downVotes": 0,
    "isExternal": 0,
    "replies": [],
    "canEdit": true,
    "images": [
      {
        "title": "",
        "url": "https://sg-test-11.slatic.net/other/roc/44621e622f874a420581a5b7e1b89504.jpg",
        "sort": 1,
        "uploadTime": 1601728227324,
        "legal": true,
        "status": "approved",
        "checkedByPeople": false,
        "width": 1024,
        "height": 768,
        "size": 362015
      },
      {
        "title": "",
        "url": "https://sg-test-11.slatic.net/other/roc/60e34b7273af4f8bdde018e9f0720392.jpg",
        "sort": 2,
        "uploadTime": 1601728227324,
        "legal": true,
        "status": "approved",
        "checkedByPeople": false,
        "width": 1024,
        "height": 768,
        "size": 363245
      },
      {
        "title": "",
        "url": "https://sg-test-11.slatic.net/other/roc/4b6f535e1a2600e1a646ae259f08bae9.jpg",
        "sort": 3,
        "uploadTime": 1601728227324,
        "legal": true,
        "status": "approved",
        "checkedByPeople": false,
        "width": 1024,
        "height": 768,
        "size": 325067
      }
    ],
    "imageQCStatus": "approved",
    "submitInfo": {
      "os": "ios",
      "source": "myreview",
      "terminal": "weex",
      "network": "WIFI"
    },
    "imageHost": "//sg-live.slatic.net",
    "showUploader": true,
    "showVideoUploader": false,
    "relevanceScore": 62.5,
    "isCompleted": 1,
    "videoId": null,
    "isVideoReady": null,
    "videoCoverUrl": null,
    "avatar": null,
    "canDownloadImage": null,
    "targetId": 171160358,
    "targetType": "item"
  },
  {
    "reviewRateId": 10808026060358,
    "reviewType": "PRODUCT_REVIEW",
    "buyerId": 764872,
    "buyerName": "saba A.",
    "buyerEmail": null,
    "realBuyerName": null,
    "isAnonymous": false,
    "tradeOrderId": null,
    "source": null,
    "clientType": "androidApp",
    "rating": 5,
    "originalRating": null,
    "reviewTitle": null,
    "reviewContent": "very good quality in this low price... bs abosrbant thodi c km hai but overall highly recommended ",
    "reviewTime": "22 Oct 2020",
    "zonedReviewTime": null,
    "likeCount": 0,
    "likeText": null,
    "isMeLike": null,
    "helpful": true,
    "rejected": false,
    "rejectionReason": null,
    "resubmissionTooltip": null,
    "resubmissionMessage": null,
    "qcReasonId": null,
    "qcDate": null,
    "isPurchased": true,
    "isGuest": false,
    "sellerId": 6005009103200,
    "sellerName": null,
    "boughtDate": "15 Oct 2020",
    "zonedBoughtDate": null,
    "reviewStatus": "approved",
    "qcTag": null,
    "qcScore": null,
    "isQced": false,
    "itemId": 171160358,
    "itemPic": "https://static-01.daraz.pk/p/6a6462c3a4cffb8b1cac5ea529f7dce4.jpg",
    "itemTitle": "BEBEM - Pack of 3 Baby diapers - Jumbo economy pack - Size 6 XXL - 44 Pcs ( 16+ kg ).",
    "itemUrl": "https://www.daraz.pk/bebem-pack-of-3-baby-diapers-jumbo-economy-pack-size-6-xxl-44-pcs-16-kg-i171160358-s1341700713.html",
    "originPrice": null,
    "salesPrice": null,
    "promotion": null,
    "skuInfo": "Size Diaper:XXL Size (14-25kg), Diaper Pack Size:44",
    "tags": null,
    "skuId": "1341700713",
    "configSku": "171160358_PK",
    "lastReviewer": "Khan, AyeshaKhan, Ayesha",
    "isReportable": 0,
    "reportStatus": null,
    "reportDate": null,
    "reportTimes": 0,
    "upVotes": 0,
    "downVotes": 0,
    "isExternal": 0,
    "replies": [],
    "canEdit": true,
    "images": [
      {
        "title": "",
        "url": "https://sg-test-11.slatic.net/other/roc/0377ca9f1a662b4bb6c2a6fab6884838.jpg",
        "sort": 1,
        "uploadTime": 1603378346061,
        "legal": true,
        "status": "approved",
        "checkedByPeople": false,
        "width": 768,
        "height": 1024,
        "size": 430605
      },
      {
        "title": "",
        "url": "https://sg-test-11.slatic.net/other/roc/80476f6ababe1c06c96bc0d62484926d.jpg",
        "sort": 2,
        "uploadTime": 1603378346061,
        "legal": true,
        "status": "approved",
        "checkedByPeople": false,
        "width": 768,
        "height": 1024,
        "size": 349295
      },
      {
        "title": "",
        "url": "https://sg-test-11.slatic.net/other/roc/d013a5bb9809257efa15a32b4de5df6d.jpg",
        "sort": 3,
        "uploadTime": 1603378346061,
        "legal": true,
        "status": "approved",
        "checkedByPeople": false,
        "width": 768,
        "height": 1024,
        "size": 366469
      }
    ],
    "imageQCStatus": "approved",
    "submitInfo": {
      "os": "ios",
      "source": "order_detail",
      "terminal": "weex",
      "network": "WIFI"
    },
    "imageHost": "//sg-live.slatic.net",
    "showUploader": true,
    "showVideoUploader": false,
    "relevanceScore": 62.35,
    "isCompleted": 1,
    "videoId": null,
    "isVideoReady": null,
    "videoCoverUrl": null,
    "avatar": null,
    "canDownloadImage": null,
    "targetId": 171160358,
    "targetType": "item"
  },
  {
    "reviewRateId": 15502666360358,
    "reviewType": "PRODUCT_REVIEW",
    "buyerId": 957586,
    "buyerName": "Samad B.",
    "buyerEmail": null,
    "realBuyerName": null,
    "isAnonymous": false,
    "tradeOrderId": null,
    "source": null,
    "clientType": "androidApp",
    "rating": 5,
    "originalRating": null,
    "reviewTitle": null,
    "reviewContent": "very nice seller. he shipped the items quick. genuine product in lowest rates",
    "reviewTime": "18 Apr 2021",
    "zonedReviewTime": null,
    "likeCount": 0,
    "likeText": null,
    "isMeLike": null,
    "helpful": true,
    "rejected": false,
    "rejectionReason": null,
    "resubmissionTooltip": null,
    "resubmissionMessage": null,
    "qcReasonId": null,
    "qcDate": null,
    "isPurchased": true,
    "isGuest": false,
    "sellerId": 6005009103200,
    "sellerName": null,
    "boughtDate": "31 Mar 2021",
    "zonedBoughtDate": null,
    "reviewStatus": "approved",
    "qcTag": null,
    "qcScore": null,
    "isQced": false,
    "itemId": 171160358,
    "itemPic": "https://static-01.daraz.pk/p/a769833298a7eabb9b49689c3dadb286.jpg",
    "itemTitle": "BEBEM - Pack of 3 Baby diapers - Jumbo economy pack - Size 6 XXL - 44 Pcs ( 16+ kg ).",
    "itemUrl": "https://www.daraz.pk/bebem-pack-of-3-baby-diapers-jumbo-economy-pack-size-6-xxl-44-pcs-16-kg-i171160358-s1341700713.html",
    "originPrice": null,
    "salesPrice": null,
    "promotion": null,
    "skuInfo": "Size Diaper:XXL Size (14-25kg), Diaper Pack Size:44",
    "tags": null,
    "skuId": "1341700713",
    "configSku": "171160358_PK",
    "lastReviewer": "Farooq, ArfeenFarooq, Arfeen",
    "isReportable": 0,
    "reportStatus": null,
    "reportDate": null,
    "reportTimes": 0,
    "upVotes": 0,
    "downVotes": 0,
    "isExternal": 0,
    "replies": [],
    "canEdit": true,
    "images": [
      {
        "title": "",
        "url": "https://sg-test-11.slatic.net/other/roc/a6edb97c76f21e012395cb2aa46b6ef4.jpg",
        "sort": 1,
        "uploadTime": 1618771998831,
        "legal": true,
        "status": "approved",
        "checkedByPeople": false,
        "width": 768,
        "height": 1024,
        "size": 450026
      },
      {
        "title": "",
        "url": "https://sg-test-11.slatic.net/other/roc/e0f97c8c52433b02e2e15e47451a5c68.jpg",
        "sort": 2,
        "uploadTime": 1618771998831,
        "legal": true,
        "status": "approved",
        "checkedByPeople": false,
        "width": 1024,
        "height": 768,
        "size": 470410
      },
      {
        "title": "",
        "url": "https://sg-test-11.slatic.net/other/roc/ceed68e78795c3cbb4967a12c869f47b.jpg",
        "sort": 3,
        "uploadTime": 1618771998831,
        "legal": true,
        "status": "approved",
        "checkedByPeople": false,
        "width": 768,
        "height": 1024,
        "size": 441726
      }
    ],
    "imageQCStatus": "approved",
    "submitInfo": {
      "os": "ios",
      "source": "myreview",
      "terminal": "weex",
      "network": "WIFI"
    },
    "imageHost": "//sg-live.slatic.net",
    "showUploader": true,
    "showVideoUploader": false,
    "relevanceScore": 60.78,
    "isCompleted": 1,
    "videoId": null,
    "isVideoReady": null,
    "videoCoverUrl": null,
    "avatar": null,
    "canDownloadImage": null,
    "targetId": 171160358,
    "targetType": "item"
  },
  {
    "reviewRateId": 10672467860358,
    "reviewType": "PRODUCT_REVIEW",
    "buyerId": 600001534946,
    "buyerName": "Muhammad J.",
    "buyerEmail": null,
    "realBuyerName": null,
    "isAnonymous": false,
    "tradeOrderId": null,
    "source": null,
    "clientType": "androidApp",
    "rating": 5,
    "originalRating": null,
    "reviewTitle": null,
    "reviewContent": "Excellent material. Speedy delivery and best quality packaging. Thank you daraz team. Extremly happy to have five star service. ",
    "reviewTime": "16 Oct 2020",
    "zonedReviewTime": null,
    "likeCount": 0,
    "likeText": null,
    "isMeLike": null,
    "helpful": true,
    "rejected": false,
    "rejectionReason": null,
    "resubmissionTooltip": null,
    "resubmissionMessage": null,
    "qcReasonId": null,
    "qcDate": null,
    "isPurchased": true,
    "isGuest": false,
    "sellerId": 6005009103200,
    "sellerName": null,
    "boughtDate": "14 Oct 2020",
    "zonedBoughtDate": null,
    "reviewStatus": "approved",
    "qcTag": null,
    "qcScore": null,
    "isQced": false,
    "itemId": 171160358,
    "itemPic": "https://static-01.daraz.pk/p/6a6462c3a4cffb8b1cac5ea529f7dce4.jpg",
    "itemTitle": "BEBEM - Pack of 3 Baby diapers - Jumbo economy pack - Size 6 XXL - 44 Pcs ( 16+ kg ).",
    "itemUrl": "https://www.daraz.pk/bebem-pack-of-3-baby-diapers-jumbo-economy-pack-size-6-xxl-44-pcs-16-kg-i171160358-s1341700713.html",
    "originPrice": null,
    "salesPrice": null,
    "promotion": null,
    "skuInfo": "Size Diaper:XXL Size (14-25kg), Diaper Pack Size:44",
    "tags": null,
    "skuId": "1341700713",
    "configSku": "171160358_PK",
    "lastReviewer": "Balani, RahulBalani, Rahul",
    "isReportable": 0,
    "reportStatus": null,
    "reportDate": null,
    "reportTimes": 0,
    "upVotes": 0,
    "downVotes": 0,
    "isExternal": 0,
    "replies": [],
    "canEdit": true,
    "images": [
      {
        "title": "",
        "url": "https://sg-test-11.slatic.net/other/roc/c37467fbc707da72a65941e1c784ad1e.jpg",
        "sort": 1,
        "uploadTime": 1602855426619,
        "legal": true,
        "status": "approved",
        "checkedByPeople": false,
        "width": 1024,
        "height": 768,
        "size": 409897
      },
      {
        "title": "",
        "url": "https://sg-test-11.slatic.net/other/roc/b9cfaf8e85a293d0ad612751bd0a3b29.jpg",
        "sort": 2,
        "uploadTime": 1602855426619,
        "legal": true,
        "status": "approved",
        "checkedByPeople": false,
        "width": 1024,
        "height": 768,
        "size": 486064
      }
    ],
    "imageQCStatus": "approved",
    "submitInfo": {
      "os": "ios",
      "source": "myreview",
      "terminal": "weex",
      "network": "WIFI"
    },
    "imageHost": "//sg-live.slatic.net",
    "showUploader": true,
    "showVideoUploader": false,
    "relevanceScore": 60.0,
    "isCompleted": 1,
    "videoId": null,
    "isVideoReady": null,
    "videoCoverUrl": null,
    "avatar": null,
    "canDownloadImage": null,
    "targetId": 171160358,
    "targetType": "item"
  },
  {
    "reviewRateId": 13895259360358,
    "reviewType": "PRODUCT_REVIEW",
    "buyerId": 476408,
    "buyerName": "Syed S.",
    "buyerEmail": null,
    "realBuyerName": null,
    "isAnonymous": false,
    "tradeOrderId": null,
    "source": null,
    "clientType": "androidApp",
    "rating": 5,
    "originalRating": null,
    "reviewTitle": null,
    "reviewContent": "good bundle offer. seller shipped on time. genuine product. thanks",
    "reviewTime": "25 Feb 2021",
    "zonedReviewTime": null,
    "likeCount": 0,
    "likeText": null,
    "isMeLike": null,
    "helpful": true,
    "rejected": false,
    "rejectionReason": null,
    "resubmissionTooltip": null,
    "resubmissionMessage": null,
    "qcReasonId": null,
    "qcDate": null,
    "isPurchased": true,
    "isGuest": false,
    "sellerId": 6005009103200,
    "sellerName": null,
    "boughtDate": "01 Feb 2021",
    "zonedBoughtDate": null,
    "reviewStatus": "approved",
    "qcTag": null,
    "qcScore": null,
    "isQced": false,
    "itemId": 171160358,
    "itemPic": "https://static-01.daraz.pk/p/6a6462c3a4cffb8b1cac5ea529f7dce4.jpg",
    "itemTitle": "BEBEM - Pack of 3 Baby diapers - Jumbo economy pack - Size 6 XXL - 44 Pcs ( 16+ kg ).",
    "itemUrl": "https://www.daraz.pk/bebem-pack-of-3-baby-diapers-jumbo-economy-pack-size-6-xxl-44-pcs-16-kg-i171160358-s1341700713.html",
    "originPrice": null,
    "salesPrice": null,
    "promotion": null,
    "skuInfo": "Size Diaper:XXL Size (14-25kg), Diaper Pack Size:44",
    "tags": null,
    "skuId": "1341700713",
    "configSku": "171160358_PK",
    "lastReviewer": "Iqbal, Muhammad AhmedIqbal, Muhammad Ahmed",
    "isReportable": 0,
    "reportStatus": null,
    "reportDate": null,
    "reportTimes": 0,
    "upVotes": 0,
    "downVotes": 0,
    "isExternal": 0,
    "replies": [],
    "canEdit": true,
    "images": [
      {
        "title": "",
        "url": "https://sg-test-11.slatic.net/other/roc/2ac6fe912ed3b82c0e27df7b3d541b95.jpg",
        "sort": 1,
        "uploadTime": 1614244751413,
        "legal": true,
        "status": "approved",
        "checkedByPeople": false,
        "width": 1024,
        "height": 768,
        "size": 456072
      },
      {
        "title": "",
        "url": "https://sg-test-11.slatic.net/other/roc/2d7676f1f495fdedd83f53596d3b6744.jpg",
        "sort": 2,
        "uploadTime": 1614244751413,
        "legal": true,
        "status": "approved",
        "checkedByPeople": false,
        "width": 1024,
        "height": 768,
        "size": 550966
      },
      {
        "title": "",
        "url": "https://sg-test-11.slatic.net/other/roc/f99f64ed8184a197dc670e452687b89c.jpg",
        "sort": 3,
        "uploadTime": 1614244751413,
        "legal": true,
        "status": "approved",
        "checkedByPeople": false,
        "width": 768,
        "height": 1024,
        "size": 456900
      }
    ],
    "imageQCStatus": "approved",
    "submitInfo": {
      "os": "ios",
      "source": "myreview",
      "terminal": "weex",
      "network": "WIFI"
    },
    "imageHost": "//sg-live.slatic.net",
    "showUploader": true,
    "showVideoUploader": false,
    "relevanceScore": 59.95,
    "isCompleted": 1,
    "videoId": null,
    "isVideoReady": null,
    "videoCoverUrl": null,
    "avatar": "https://graph.facebook.com/10156831297666055/picture",
    "canDownloadImage": null,
    "targetId": 171160358,
    "targetType": "item"
  },
  {
    "reviewRateId": 10838651360358,
    "reviewType": "PRODUCT_REVIEW",
    "buyerId": 2277931,
    "buyerName": "Ahmed B.",
    "buyerEmail": null,
    "realBuyerName": null,
    "isAnonymous": false,
    "tradeOrderId": null,
    "source": null,
    "clientType": "androidApp",
    "rating": 5,
    "originalRating": null,
    "reviewTitle": null,
    "reviewContent": "Good & Genuine product with great discount\nRecommended \ud83d\ude0a",
    "reviewTime": "27 Nov 2020",
    "zonedReviewTime": null,
    "likeCount": 0,
    "likeText": null,
    "isMeLike": null,
    "helpful": true,
    "rejected": false,
    "rejectionReason": null,
    "resubmissionTooltip": null,
    "resubmissionMessage": null,
    "qcReasonId": null,
    "qcDate": null,
    "isPurchased": true,
    "isGuest": false,
    "sellerId": 6005009103200,
    "sellerName": null,
    "boughtDate": "14 Oct 2020",
    "zonedBoughtDate": null,
    "reviewStatus": "approved",
    "qcTag": null,
    "qcScore": null,
    "isQced": false,
    "itemId": 171160358,
    "itemPic": "https://static-01.daraz.pk/p/6a6462c3a4cffb8b1cac5ea529f7dce4.jpg",
    "itemTitle": "BEBEM - Pack of 3 Baby diapers - Jumbo economy pack - Size 6 XXL - 44 Pcs ( 16+ kg ).",
    "itemUrl": "https://www.daraz.pk/bebem-pack-of-3-baby-diapers-jumbo-economy-pack-size-6-xxl-44-pcs-16-kg-i171160358-s1341700713.html",
    "originPrice": null,
    "salesPrice": null,
    "promotion": null,
    "skuInfo": "Size Diaper:XXL Size (14-25kg), Diaper Pack Size:44",
    "tags": null,
    "skuId": "1341700713",
    "configSku": "171160358_PK",
    "lastReviewer": "Khan, AyeshaKhan, Ayesha",
    "isReportable": 0,
    "reportStatus": null,
    "reportDate": null,
    "reportTimes": 0,
    "upVotes": 0,
    "downVotes": 0,
    "isExternal": 0,
    "replies": [],
    "canEdit": true,
    "images": [
      {
        "title": "",
        "url": "https://sg-test-11.slatic.net/other/roc/f627a521327c0299872847aafde38d28.jpg",
        "sort": 1,
        "uploadTime": 1606472958000,
        "legal": true,
        "status": "approved",
        "checkedByPeople": false,
        "width": 921,
        "height": 691,
        "size": 411630
      },
      {
        "title": "",
        "url": "https://sg-test-11.slatic.net/other/roc/f1d7440e7b3f7c3775e35dfbd54bfce5.jpg",
        "sort": 2,
        "uploadTime": 1606473182065,
        "legal": true,
        "status": "approved",
        "checkedByPeople": false,
        "width": 691,
        "height": 921,
        "size": 477758
      },
      {
        "title": "",
        "url": "https://sg-test-11.slatic.net/other/roc/5a0353572d9a3628a71f77e046394914.jpg",
        "sort": 3,
        "uploadTime": 1606473182065,
        "legal": true,
        "status": "approved",
        "checkedByPeople": false,
        "width": 691,
        "height": 921,
        "size": 340111
      }
    ],
    "imageQCStatus": "approved",
    "submitInfo": {
      "os": "ios",
      "source": "myreview",
      "terminal": "weex",
      "network": "WIFI"
    },
    "imageHost": "//sg-live.slatic.net",
    "showUploader": true,
    "showVideoUploader": false,
    "relevanceScore": 59.28,
    "isCompleted": 1,
    "videoId": null,
    "isVideoReady": null,
    "videoCoverUrl": null,
    "avatar": "https://graph.facebook.com/10211589557964501/picture",
    "canDownloadImage": null,
    "targetId": 171160358,
    "targetType": "item"
  },
  {
    "reviewRateId": 12070482860358,
    "reviewType": "PRODUCT_REVIEW",
    "buyerId": 145200,
    "buyerName": "Zia U.",
    "buyerEmail": null,
    "realBuyerName": null,
    "isAnonymous": false,
    "tradeOrderId": null,
    "source": null,
    "clientType": "androidApp",
    "rating": 5,
    "originalRating": null,
    "reviewTitle": null,
    "reviewContent": "Carefully packed and timely delivery \ud83d\udc4d",
    "reviewTime": "07 Dec 2020",
    "zonedReviewTime": null,
    "likeCount": 0,
    "likeText": null,
    "isMeLike": null,
    "helpful": true,
    "rejected": false,
    "rejectionReason": null,
    "resubmissionTooltip": null,
    "resubmissionMessage": null,
    "qcReasonId": null,
    "qcDate": null,
    "isPurchased": true,
    "isGuest": false,
    "sellerId": 6005009103200,
    "sellerName": null,
    "boughtDate": "27 Nov 2020",
    "zonedBoughtDate": null,
    "reviewStatus": "approved",
    "qcTag": null,
    "qcScore": null,
    "isQced": false,
    "itemId": 171160358,
    "itemPic": "https://static-01.daraz.pk/p/6a6462c3a4cffb8b1cac5ea529f7dce4.jpg",
    "itemTitle": "BEBEM - Pack of 3 Baby diapers - Jumbo economy pack - Size 6 XXL - 44 Pcs ( 16+ kg ).",
    "itemUrl": "https://www.daraz.pk/bebem-pack-of-3-baby-diapers-jumbo-economy-pack-size-6-xxl-44-pcs-16-kg-i171160358-s1341700713.html",
    "originPrice": null,
    "salesPrice": null,
    "promotion": null,
    "skuInfo": "Size Diaper:XXL Size (14-25kg), Diaper Pack Size:44",
    "tags": null,
    "skuId": "1341700713",
    "configSku": "171160358_PK",
    "lastReviewer": "Iqbal, Muhammad AhmedIqbal, Muhammad Ahmed",
    "isReportable": 0,
    "reportStatus": null,
    "reportDate": null,
    "reportTimes": 0,
    "upVotes": 0,
    "downVotes": 0,
    "isExternal": 0,
    "replies": [],
    "canEdit": true,
    "images": [
      {
        "title": "",
        "url": "https://sg-test-11.slatic.net/other/roc/a8a22d4f1dd7bc4e0050ba397559fbc2.jpg",
        "sort": 1,
        "uploadTime": 1607351510834,
        "legal": true,
        "status": "approved",
        "checkedByPeople": false,
        "width": 1024,
        "height": 768,
        "size": 419912
      },
      {
        "title": "",
        "url": "https://sg-test-11.slatic.net/other/roc/f184567b5ff5d4877c3a872794d24e25.jpg",
        "sort": 2,
        "uploadTime": 1607351510834,
        "legal": true,
        "status": "approved",
        "checkedByPeople": false,
        "width": 768,
        "height": 1024,
        "size": 410951
      },
      {
        "title": "",
        "url": "https://sg-test-11.slatic.net/other/roc/36a35ee828cbd996d7dd1b7163ddc004.jpg",
        "sort": 3,
        "uploadTime": 1607351510834,
        "legal": true,
        "status": "approved",
        "checkedByPeople": false,
        "width": 768,
        "height": 1024,
        "size": 491436
      }
    ],
    "imageQCStatus": "approved",
    "submitInfo": {
      "os": "ios",
      "source": "myreview",
      "terminal": "weex",
      "network": "WIFI"
    },
    "imageHost": "//sg-live.slatic.net",
    "showUploader": true,
    "showVideoUploader": false,
    "relevanceScore": 57.93,
    "isCompleted": 1,
    "videoId": null,
    "isVideoReady": null,
    "videoCoverUrl": null,
    "avatar": "https://graph.facebook.com/3501956563175139/picture",
    "canDownloadImage": null,
    "targetId": 171160358,
    "targetType": "item"
  },
  {
    "reviewRateId": 12144071660358,
    "reviewType": "PRODUCT_REVIEW",
    "buyerId": 600000536480,
    "buyerName": "Rizwan",
    "buyerEmail": null,
    "realBuyerName": null,
    "isAnonymous": false,
    "tradeOrderId": null,
    "source": null,
    "clientType": "androidApp",
    "rating": 3,
    "originalRating": null,
    "reviewTitle": null,
    "reviewContent": "Good in the price\nMolfix is better ",
    "reviewTime": "09 Dec 2020",
    "zonedReviewTime": null,
    "likeCount": 0,
    "likeText": null,
    "isMeLike": null,
    "helpful": true,
    "rejected": false,
    "rejectionReason": null,
    "resubmissionTooltip": null,
    "resubmissionMessage": null,
    "qcReasonId": null,
    "qcDate": null,
    "isPurchased": true,
    "isGuest": false,
    "sellerId": 6005009103200,
    "sellerName": null,
    "boughtDate": "26 Nov 2020",
    "zonedBoughtDate": null,
    "reviewStatus": "approved",
    "qcTag": null,
    "qcScore": null,
    "isQced": false,
    "itemId": 171160358,
    "itemPic": "https://static-01.daraz.pk/p/6a6462c3a4cffb8b1cac5ea529f7dce4.jpg",
    "itemTitle": "BEBEM - Pack of 3 Baby diapers - Jumbo economy pack - Size 6 XXL - 44 Pcs ( 16+ kg ).",
    "itemUrl": "https://www.daraz.pk/bebem-pack-of-3-baby-diapers-jumbo-economy-pack-size-6-xxl-44-pcs-16-kg-i171160358-s1341700713.html",
    "originPrice": null,
    "salesPrice": null,
    "promotion": null,
    "skuInfo": "Size Diaper:XXL Size (14-25kg), Diaper Pack Size:44",
    "tags": null,
    "skuId": "1341700713",
    "configSku": "171160358_PK",
    "lastReviewer": "Khan, AyeshaKhan, Ayesha",
    "isReportable": 0,
    "reportStatus": null,
    "reportDate": null,
    "reportTimes": 0,
    "upVotes": 0,
    "downVotes": 0,
    "isExternal": 0,
    "replies": [],
    "canEdit": true,
    "images": [
      {
        "title": "",
        "url": "https://sg-test-11.slatic.net/other/roc/aa6c9d0ac379fc6354ae3acb2bd86b48.jpg",
        "sort": 1,
        "uploadTime": 1607515192120,
        "legal": true,
        "status": "approved",
        "checkedByPeople": false,
        "width": 756,
        "height": 1008,
        "size": 584921
      },
      {
        "title": "",
        "url": "https://sg-test-11.slatic.net/other/roc/6233545d7400b683e51ea346f6972f85.jpg",
        "sort": 2,
        "uploadTime": 1607515192120,
        "legal": true,
        "status": "approved",
        "checkedByPeople": false,
        "width": 756,
        "height": 1008,
        "size": 532361
      },
      {
        "title": "",
        "url": "https://sg-test-11.slatic.net/other/roc/e0df191fa5bb501f5cc23f966ce7d4e3.jpg",
        "sort": 3,
        "uploadTime": 1607515192120,
        "legal": true,
        "status": "approved",
        "checkedByPeople": false,
        "width": 756,
        "height": 1008,
        "size": 479606
      }
    ],
    "imageQCStatus": "approved",
    "submitInfo": {
      "os": "ios",
      "source": "myreview",
      "terminal": "weex",
      "network": "WIFI"
    },
    "imageHost": "//sg-live.slatic.net",
    "showUploader": true,
    "showVideoUploader": false,
    "relevanceScore": 57.63,
    "isCompleted": 1,
    "videoId": null,
    "isVideoReady": null,
    "videoCoverUrl": null,
    "avatar": "https://lh6.googleusercontent.com/-RJXXf3VoiY0/AAAAAAAAAAI/AAAAAAAAFqI/4PkfRre_tNQ/s96-c/photo.jpg",
    "canDownloadImage": null,
    "targetId": 171160358,
    "targetType": "item"
  },
  {
    "reviewRateId": 14277899460358,
    "reviewType": "PRODUCT_REVIEW",
    "buyerId": 843941,
    "buyerName": "B***.",
    "buyerEmail": null,
    "realBuyerName": null,
    "isAnonymous": true,
    "tradeOrderId": null,
    "source": null,
    "clientType": "androidApp",
    "rating": 5,
    "originalRating": null,
    "reviewTitle": null,
    "reviewContent": "Original product. Fast delivery",
    "reviewTime": "19 Feb 2021",
    "zonedReviewTime": null,
    "likeCount": 0,
    "likeText": null,
    "isMeLike": null,
    "helpful": true,
    "rejected": false,
    "rejectionReason": null,
    "resubmissionTooltip": null,
    "resubmissionMessage": null,
    "qcReasonId": null,
    "qcDate": null,
    "isPurchased": true,
    "isGuest": false,
    "sellerId": 6005009103200,
    "sellerName": null,
    "boughtDate": "17 Feb 2021",
    "zonedBoughtDate": null,
    "reviewStatus": "approved",
    "qcTag": null,
    "qcScore": null,
    "isQced": false,
    "itemId": 171160358,
    "itemPic": "https://static-01.daraz.pk/p/6a6462c3a4cffb8b1cac5ea529f7dce4.jpg",
    "itemTitle": "BEBEM - Pack of 3 Baby diapers - Jumbo economy pack - Size 6 XXL - 44 Pcs ( 16+ kg ).",
    "itemUrl": "https://www.daraz.pk/bebem-pack-of-3-baby-diapers-jumbo-economy-pack-size-6-xxl-44-pcs-16-kg-i171160358-s1341700713.html",
    "originPrice": null,
    "salesPrice": null,
    "promotion": null,
    "skuInfo": "Size Diaper:XXL Size (14-25kg), Diaper Pack Size:44",
    "tags": null,
    "skuId": "1341700713",
    "configSku": "171160358_PK",
    "lastReviewer": "Iqbal, Muhammad AhmedIqbal, Muhammad Ahmed",
    "isReportable": 0,
    "reportStatus": null,
    "reportDate": null,
    "reportTimes": 0,
    "upVotes": 0,
    "downVotes": 0,
    "isExternal": 0,
    "replies": [],
    "canEdit": true,
    "images": [
      {
        "title": "",
        "url": "https://sg-test-11.slatic.net/other/roc/cf36315d8f700f987846daaf31340311.jpg",
        "sort": 1,
        "uploadTime": 1613740505007,
        "legal": true,
        "status": "approved",
        "checkedByPeople": false,
        "width": 768,
        "height": 1024,
        "size": 470406
      },
      {
        "title": "",
        "url": "https://sg-test-11.slatic.net/other/roc/d14e627e897a85d2fb5f449e0639966a.jpg",
        "sort": 2,
        "uploadTime": 1613740505007,
        "legal": true,
        "status": "approved",
        "checkedByPeople": false,
        "width": 768,
        "height": 1024,
        "size": 465545
      }
    ],
    "imageQCStatus": "approved",
    "submitInfo": {
      "os": "ios",
      "source": "myreview",
      "terminal": "weex",
      "network": "WIFI"
    },
    "imageHost": "//sg-live.slatic.net",
    "showUploader": true,
    "showVideoUploader": false,
    "relevanceScore": 54.83,
    "isCompleted": 1,
    "videoId": null,
    "isVideoReady": null,
    "videoCoverUrl": null,
    "avatar": null,
    "canDownloadImage": null,
    "targetId": 171160358,
    "targetType": "item"
  },
  {
    "reviewRateId": 11913004160358,
    "reviewType": "PRODUCT_REVIEW",
    "buyerId": 1119970,
    "buyerName": "Adeel K.",
    "buyerEmail": null,
    "realBuyerName": null,
    "isAnonymous": false,
    "tradeOrderId": null,
    "source": null,
    "clientType": "androidApp",
    "rating": 5,
    "originalRating": null,
    "reviewTitle": null,
    "reviewContent": "Good Packaging and quality...",
    "reviewTime": "03 Dec 2020",
    "zonedReviewTime": null,
    "likeCount": 0,
    "likeText": null,
    "isMeLike": null,
    "helpful": true,
    "rejected": false,
    "rejectionReason": null,
    "resubmissionTooltip": null,
    "resubmissionMessage": null,
    "qcReasonId": null,
    "qcDate": null,
    "isPurchased": true,
    "isGuest": false,
    "sellerId": 6005009103200,
    "sellerName": null,
    "boughtDate": "17 Nov 2020",
    "zonedBoughtDate": null,
    "reviewStatus": "approved",
    "qcTag": null,
    "qcScore": null,
    "isQced": false,
    "itemId": 171160358,
    "itemPic": "https://static-01.daraz.pk/p/6a6462c3a4cffb8b1cac5ea529f7dce4.jpg",
    "itemTitle": "BEBEM - Pack of 3 Baby diapers - Jumbo economy pack - Size 6 XXL - 44 Pcs ( 16+ kg ).",
    "itemUrl": "https://www.daraz.pk/bebem-pack-of-3-baby-diapers-jumbo-economy-pack-size-6-xxl-44-pcs-16-kg-i171160358-s1341700713.html",
    "originPrice": null,
    "salesPrice": null,
    "promotion": null,
    "skuInfo": "Size Diaper:XXL Size (14-25kg), Diaper Pack Size:44",
    "tags": null,
    "skuId": "1341700713",
    "configSku": "171160358_PK",
    "lastReviewer": "Iqbal, Muhammad AhmedIqbal, Muhammad Ahmed",
    "isReportable": 0,
    "reportStatus": null,
    "reportDate": null,
    "reportTimes": 0,
    "upVotes": 0,
    "downVotes": 0,
    "isExternal": 0,
    "replies": [],
    "canEdit": true,
    "images": [
      {
        "title": "",
        "url": "https://sg-test-11.slatic.net/other/roc/5ac11951ff6a77639ae91eecd53ebaa5.jpg",
        "sort": 1,
        "uploadTime": 1606939580542,
        "legal": true,
        "status": "approved",
        "checkedByPeople": false,
        "width": 1024,
        "height": 768,
        "size": 605346
      },
      {
        "title": "",
        "url": "https://sg-test-11.slatic.net/other/roc/65c53dbe0fa41fd7c26de2b4f8c65b59.jpg",
        "sort": 2,
        "uploadTime": 1606939580542,
        "legal": true,
        "status": "approved",
        "checkedByPeople": false,
        "width": 1024,
        "height": 768,
        "size": 534475
      }
    ],
    "imageQCStatus": "approved",
    "submitInfo": {
      "os": "ios",
      "source": "myreview",
      "terminal": "weex",
      "network": "WIFI"
    },
    "imageHost": "//sg-live.slatic.net",
    "showUploader": true,
    "showVideoUploader": false,
    "relevanceScore": 54.68,
    "isCompleted": 1,
    "videoId": null,
    "isVideoReady": null,
    "videoCoverUrl": null,
    "avatar": null,
    "canDownloadImage": null,
    "targetId": 171160358,
    "targetType": "item"
  },
  {
    "reviewRateId": 14608418460358,
    "reviewType": "PRODUCT_REVIEW",
    "buyerId": 763434,
    "buyerName": "Ghulam H.",
    "buyerEmail": null,
    "realBuyerName": null,
    "isAnonymous": false,
    "tradeOrderId": null,
    "source": null,
    "clientType": "androidApp",
    "rating": 5,
    "originalRating": null,
    "reviewTitle": null,
    "reviewContent": "same as description thanks you so much seller and daraz",
    "reviewTime": "05 Mar 2021",
    "zonedReviewTime": null,
    "likeCount": 0,
    "likeText": null,
    "isMeLike": null,
    "helpful": true,
    "rejected": false,
    "rejectionReason": null,
    "resubmissionTooltip": null,
    "resubmissionMessage": null,
    "qcReasonId": null,
    "qcDate": null,
    "isPurchased": true,
    "isGuest": false,
    "sellerId": 6005009103200,
    "sellerName": null,
    "boughtDate": "03 Mar 2021",
    "zonedBoughtDate": null,
    "reviewStatus": "approved",
    "qcTag": null,
    "qcScore": null,
    "isQced": false,
    "itemId": 171160358,
    "itemPic": "https://static-01.daraz.pk/p/6a6462c3a4cffb8b1cac5ea529f7dce4.jpg",
    "itemTitle": "BEBEM - Pack of 3 Baby diapers - Jumbo economy pack - Size 6 XXL - 44 Pcs ( 16+ kg ).",
    "itemUrl": "https://www.daraz.pk/bebem-pack-of-3-baby-diapers-jumbo-economy-pack-size-6-xxl-44-pcs-16-kg-i171160358-s1341700713.html",
    "originPrice": null,
    "salesPrice": null,
    "promotion": null,
    "skuInfo": "Size Diaper:XXL Size (14-25kg), Diaper Pack Size:44",
    "tags": null,
    "skuId": "1341700713",
    "configSku": "171160358_PK",
    "lastReviewer": "Khan, AyeshaKhan, Ayesha",
    "isReportable": 0,
    "reportStatus": null,
    "reportDate": null,
    "reportTimes": 0,
    "upVotes": 0,
    "downVotes": 0,
    "isExternal": 0,
    "replies": [],
    "canEdit": true,
    "images": [
      {
        "title": "",
        "url": "https://sg-test-11.slatic.net/other/roc/a7f5cf5da47e05b122114a13aeca5f02.jpg",
        "sort": 1,
        "uploadTime": 1614936994075,
        "legal": true,
        "status": "approved",
        "checkedByPeople": false,
        "width": 921,
        "height": 691,
        "size": 469848
      }
    ],
    "imageQCStatus": "approved",
    "submitInfo": {
      "os": "ios",
      "source": "myreview",
      "terminal": "weex",
      "network": "WIFI"
    },
    "imageHost": "//sg-live.slatic.net",
    "showUploader": true,
    "showVideoUploader": false,
    "relevanceScore": 54.13,
    "isCompleted": 1,
    "videoId": null,
    "isVideoReady": null,
    "videoCoverUrl": null,
    "avatar": null,
    "canDownloadImage": null,
    "targetId": 171160358,
    "targetType": "item"
  },
  {
    "reviewRateId": 12165050760358,
    "reviewType": "PRODUCT_REVIEW",
    "buyerId": 529546,
    "buyerName": "Umer T.",
    "buyerEmail": null,
    "realBuyerName": null,
    "isAnonymous": false,
    "tradeOrderId": null,
    "source": null,
    "clientType": "androidApp",
    "rating": 5,
    "originalRating": null,
    "reviewTitle": null,
    "reviewContent": "Good quality.ma aik or order karnay laga.thanks",
    "reviewTime": "05 Dec 2020",
    "zonedReviewTime": null,
    "likeCount": 0,
    "likeText": null,
    "isMeLike": null,
    "helpful": true,
    "rejected": false,
    "rejectionReason": null,
    "resubmissionTooltip": null,
    "resubmissionMessage": null,
    "qcReasonId": null,
    "qcDate": null,
    "isPurchased": true,
    "isGuest": false,
    "sellerId": 6005009103200,
    "sellerName": null,
    "boughtDate": "30 Nov 2020",
    "zonedBoughtDate": null,
    "reviewStatus": "approved",
    "qcTag": null,
    "qcScore": null,
    "isQced": false,
    "itemId": 171160358,
    "itemPic": "https://static-01.daraz.pk/p/6a6462c3a4cffb8b1cac5ea529f7dce4.jpg",
    "itemTitle": "BEBEM - Pack of 3 Baby diapers - Jumbo economy pack - Size 6 XXL - 44 Pcs ( 16+ kg ).",
    "itemUrl": "https://www.daraz.pk/bebem-pack-of-3-baby-diapers-jumbo-economy-pack-size-6-xxl-44-pcs-16-kg-i171160358-s1341700713.html",
    "originPrice": null,
    "salesPrice": null,
    "promotion": null,
    "skuInfo": "Size Diaper:XXL Size (14-25kg), Diaper Pack Size:44",
    "tags": null,
    "skuId": "1341700713",
    "configSku": "171160358_PK",
    "lastReviewer": "Khan, AyeshaKhan, Ayesha",
    "isReportable": 0,
    "reportStatus": null,
    "reportDate": null,
    "reportTimes": 0,
    "upVotes": 0,
    "downVotes": 0,
    "isExternal": 0,
    "replies": [],
    "canEdit": true,
    "images": [
      {
        "title": "",
        "url": "https://sg-test-11.slatic.net/other/roc/4dd7f7b88cd7580066c61d7f42ac58d7.jpg",
        "sort": 1,
        "uploadTime": 1607154836186,
        "legal": true,
        "status": "approved",
        "checkedByPeople": false,
        "width": 432,
        "height": 984,
        "size": 252592
      }
    ],
    "imageQCStatus": "approved",
    "submitInfo": {
      "os": "ios",
      "source": "myreview",
      "terminal": "weex",
      "network": "WIFI"
    },
    "imageHost": "//sg-live.slatic.net",
    "showUploader": true,
    "showVideoUploader": false,
    "relevanceScore": 53.53,
    "isCompleted": 1,
    "videoId": null,
    "isVideoReady": null,
    "videoCoverUrl": null,
    "avatar": "https://lh3.googleusercontent.com/a-/AOh14GjCHolWN1enClA0P7FvgppF9RzzV9T4joD1CvS1=s96-c",
    "canDownloadImage": null,
    "targetId": 171160358,
    "targetType": "item"
  },
  {
    "reviewRateId": 10610263860358,
    "reviewType": "PRODUCT_REVIEW",
    "buyerId": 600024948170,
    "buyerName": "mustafa K.",
    "buyerEmail": null,
    "realBuyerName": null,
    "isAnonymous": false,
    "tradeOrderId": null,
    "source": null,
    "clientType": "androidApp",
    "rating": 5,
    "originalRating": null,
    "reviewTitle": null,
    "reviewContent": "zabardast good quality n fast delivery\ud83d\udc4d",
    "reviewTime": "13 Oct 2020",
    "zonedReviewTime": null,
    "likeCount": 0,
    "likeText": null,
    "isMeLike": null,
    "helpful": true,
    "rejected": false,
    "rejectionReason": null,
    "resubmissionTooltip": null,
    "resubmissionMessage": null,
    "qcReasonId": null,
    "qcDate": null,
    "isPurchased": true,
    "isGuest": false,
    "sellerId": 6005009103200,
    "sellerName": null,
    "boughtDate": "10 Oct 2020",
    "zonedBoughtDate": null,
    "reviewStatus": "approved",
    "qcTag": null,
    "qcScore": null,
    "isQced": false,
    "itemId": 171160358,
    "itemPic": "https://static-01.daraz.pk/p/6a6462c3a4cffb8b1cac5ea529f7dce4.jpg",
    "itemTitle": "BEBEM - Pack of 3 Baby diapers - Jumbo economy pack - Size 6 XXL - 44 Pcs ( 16+ kg ).",
    "itemUrl": "https://www.daraz.pk/bebem-pack-of-3-baby-diapers-jumbo-economy-pack-size-6-xxl-44-pcs-16-kg-i171160358-s1341700713.html",
    "originPrice": null,
    "salesPrice": null,
    "promotion": null,
    "skuInfo": "Size Diaper:XXL Size (14-25kg), Diaper Pack Size:44",
    "tags": null,
    "skuId": "1341700713",
    "configSku": "171160358_PK",
    "lastReviewer": "Iqbal, Muhammad AhmedIqbal, Muhammad Ahmed",
    "isReportable": 0,
    "reportStatus": null,
    "reportDate": null,
    "reportTimes": 0,
    "upVotes": 0,
    "downVotes": 0,
    "isExternal": 0,
    "replies": [],
    "canEdit": true,
    "images": [
      {
        "title": "",
        "url": "https://sg-test-11.slatic.net/other/roc/1ad201936ad78b7167922fd3c48172a8.jpg",
        "sort": 1,
        "uploadTime": 1602583878831,
        "legal": true,
        "status": "approved",
        "checkedByPeople": false,
        "width": 460,
        "height": 921,
        "size": 319047
      }
    ],
    "imageQCStatus": "approved",
    "submitInfo": {
      "os": "ios",
      "source": "order_detail",
      "terminal": "weex",
      "network": "WIFI"
    },
    "imageHost": "//sg-live.slatic.net",
    "showUploader": true,
    "showVideoUploader": false,
    "relevanceScore": 53.0,
    "isCompleted": 1,
    "videoId": null,
    "isVideoReady": null,
    "videoCoverUrl": null,
    "avatar": null,
    "canDownloadImage": null,
    "targetId": 171160358,
    "targetType": "item"
  },
  {
    "reviewRateId": 14472499560358,
    "reviewType": "PRODUCT_REVIEW",
    "buyerId": 1770346,
    "buyerName": "Muhammad T.",
    "buyerEmail": null,
    "realBuyerName": null,
    "isAnonymous": false,
    "tradeOrderId": null,
    "source": null,
    "clientType": "desktop",
    "rating": 5,
    "originalRating": null,
    "reviewTitle": null,
    "reviewContent": "05 stars from my side. But i must say the price was lower when i started buying from the seller, gradually it increased.",
    "reviewTime": "12 Mar 2021",
    "zonedReviewTime": null,
    "likeCount": 0,
    "likeText": null,
    "isMeLike": null,
    "helpful": true,
    "rejected": false,
    "rejectionReason": null,
    "resubmissionTooltip": null,
    "resubmissionMessage": null,
    "qcReasonId": null,
    "qcDate": null,
    "isPurchased": true,
    "isGuest": false,
    "sellerId": 6005009103200,
    "sellerName": null,
    "boughtDate": "25 Feb 2021",
    "zonedBoughtDate": null,
    "reviewStatus": "approved",
    "qcTag": null,
    "qcScore": null,
    "isQced": false,
    "itemId": 171160358,
    "itemPic": "https://static-01.daraz.pk/p/6a6462c3a4cffb8b1cac5ea529f7dce4.jpg",
    "itemTitle": "BEBEM - Pack of 3 Baby diapers - Jumbo economy pack - Size 6 XXL - 44 Pcs ( 16+ kg ).",
    "itemUrl": "https://www.daraz.pk/bebem-pack-of-3-baby-diapers-jumbo-economy-pack-size-6-xxl-44-pcs-16-kg-i171160358-s1341700713.html",
    "originPrice": null,
    "salesPrice": null,
    "promotion": null,
    "skuInfo": "Size Diaper:XXL Size (14-25kg), Diaper Pack Size:44",
    "tags": null,
    "skuId": "1341700713",
    "configSku": "171160358_PK",
    "lastReviewer": "Naveed Malik, MustafaNaveed Malik, Mustafa",
    "isReportable": 0,
    "reportStatus": null,
    "reportDate": null,
    "reportTimes": 0,
    "upVotes": 0,
    "downVotes": 0,
    "isExternal": 0,
    "replies": [],
    "canEdit": true,
    "images": null,
    "imageQCStatus": null,
    "submitInfo": {
      "os": "PC",
      "source": "myreview",
      "terminal": "PC",
      "network": "WIFI"
    },
    "imageHost": "//sg-live.slatic.net",
    "showUploader": true,
    "showVideoUploader": false,
    "relevanceScore": 40.0,
    "isCompleted": 1,
    "videoId": null,
    "isVideoReady": null,
    "videoCoverUrl": null,
    "avatar": null,
    "canDownloadImage": null,
    "targetId": 171160358,
    "targetType": "item"
  },
  {
    "reviewRateId": 14241673960358,
    "reviewType": "PRODUCT_REVIEW",
    "buyerId": 600025221556,
    "buyerName": "mrs U.",
    "buyerEmail": null,
    "realBuyerName": null,
    "isAnonymous": false,
    "tradeOrderId": null,
    "source": null,
    "clientType": "androidApp",
    "rating": 5,
    "originalRating": null,
    "reviewTitle": null,
    "reviewContent": "masha Allah today i recieved my parcel . always recieve at time. i would like to recommend it all mothers. these dypers are just like pampers . same quality but lowest prices .. and i also request to the seller that plz dont increase the prices .. a couple of month ago i purchased them from rupees 2300 and you have increased the price uptill now 3100.. plz dont increase prices now.. overall its a good purchase and best quality dypers thisis my 8th order",
    "reviewTime": "18 Feb 2021",
    "zonedReviewTime": null,
    "likeCount": 0,
    "likeText": null,
    "isMeLike": null,
    "helpful": true,
    "rejected": false,
    "rejectionReason": null,
    "resubmissionTooltip": null,
    "resubmissionMessage": null,
    "qcReasonId": null,
    "qcDate": null,
    "isPurchased": true,
    "isGuest": false,
    "sellerId": 6005009103200,
    "sellerName": null,
    "boughtDate": "14 Feb 2021",
    "zonedBoughtDate": null,
    "reviewStatus": "approved",
    "qcTag": null,
    "qcScore": null,
    "isQced": false,
    "itemId": 171160358,
    "itemPic": "https://static-01.daraz.pk/p/6a6462c3a4cffb8b1cac5ea529f7dce4.jpg",
    "itemTitle": "BEBEM - Pack of 3 Baby diapers - Jumbo economy pack - Size 6 XXL - 44 Pcs ( 16+ kg ).",
    "itemUrl": "https://www.daraz.pk/bebem-pack-of-3-baby-diapers-jumbo-economy-pack-size-6-xxl-44-pcs-16-kg-i171160358-s1341700713.html",
    "originPrice": null,
    "salesPrice": null,
    "promotion": null,
    "skuInfo": "Size Diaper:XXL Size (14-25kg), Diaper Pack Size:44",
    "tags": null,
    "skuId": "1341700713",
    "configSku": "171160358_PK",
    "lastReviewer": "Naveed Malik, MustafaNaveed Malik, Mustafa",
    "isReportable": 0,
    "reportStatus": null,
    "reportDate": null,
    "reportTimes": 0,
    "upVotes": 0,
    "downVotes": 0,
    "isExternal": 0,
    "replies": [],
    "canEdit": true,
    "images": null,
    "imageQCStatus": null,
    "submitInfo": {
      "os": "ios",
      "source": "myreview",
      "terminal": "weex",
      "network": "WIFI"
    },
    "imageHost": "//sg-live.slatic.net",
    "showUploader": true,
    "showVideoUploader": false,
    "relevanceScore": 40.0,
    "isCompleted": 1,
    "videoId": null,
    "isVideoReady": null,
    "videoCoverUrl": null,
    "avatar": null,
    "canDownloadImage": null,
    "targetId": 171160358,
    "targetType": "item"
  },
  {
    "reviewRateId": 11690052760358,
    "reviewType": "PRODUCT_REVIEW",
    "buyerId": 600019737244,
    "buyerName": "Adil Q.",
    "buyerEmail": null,
    "realBuyerName": null,
    "isAnonymous": false,
    "tradeOrderId": null,
    "source": null,
    "clientType": "androidApp",
    "rating": 5,
    "originalRating": null,
    "reviewTitle": null,
    "reviewContent": "The product received is genuinely as described but In packaging of 22 pieces per pack. Totally satisfied with the delivery and response from seller. ",
    "reviewTime": "19 Nov 2020",
    "zonedReviewTime": null,
    "likeCount": 0,
    "likeText": null,
    "isMeLike": null,
    "helpful": true,
    "rejected": false,
    "rejectionReason": null,
    "resubmissionTooltip": null,
    "resubmissionMessage": null,
    "qcReasonId": null,
    "qcDate": null,
    "isPurchased": true,
    "isGuest": false,
    "sellerId": 6005009103200,
    "sellerName": null,
    "boughtDate": "15 Nov 2020",
    "zonedBoughtDate": null,
    "reviewStatus": "approved",
    "qcTag": null,
    "qcScore": null,
    "isQced": false,
    "itemId": 171160358,
    "itemPic": "https://static-01.daraz.pk/p/6a6462c3a4cffb8b1cac5ea529f7dce4.jpg",
    "itemTitle": "BEBEM - Pack of 3 Baby diapers - Jumbo economy pack - Size 6 XXL - 44 Pcs ( 16+ kg ).",
    "itemUrl": "https://www.daraz.pk/bebem-pack-of-3-baby-diapers-jumbo-economy-pack-size-6-xxl-44-pcs-16-kg-i171160358-s1341700713.html",
    "originPrice": null,
    "salesPrice": null,
    "promotion": null,
    "skuInfo": "Size Diaper:XXL Size (14-25kg), Diaper Pack Size:44",
    "tags": null,
    "skuId": "1341700713",
    "configSku": "171160358_PK",
    "lastReviewer": "Balani, RahulBalani, Rahul",
    "isReportable": 0,
    "reportStatus": null,
    "reportDate": null,
    "reportTimes": 0,
    "upVotes": 0,
    "downVotes": 0,
    "isExternal": 0,
    "replies": [],
    "canEdit": true,
    "images": null,
    "imageQCStatus": null,
    "submitInfo": {
      "os": "ios",
      "source": "myreview",
      "terminal": "weex",
      "network": "UNKNOWN"
    },
    "imageHost": "//sg-live.slatic.net",
    "showUploader": true,
    "showVideoUploader": false,
    "relevanceScore": 40.0,
    "isCompleted": 1,
    "videoId": null,
    "isVideoReady": null,
    "videoCoverUrl": null,
    "avatar": "https://graph.facebook.com/2897991703569722/picture",
    "canDownloadImage": null,
    "targetId": 171160358,
    "targetType": "item"
  },
  {
    "reviewRateId": 11580879360358,
    "reviewType": "PRODUCT_REVIEW",
    "buyerId": 764872,
    "buyerName": "saba A.",
    "buyerEmail": null,
    "realBuyerName": null,
    "isAnonymous": false,
    "tradeOrderId": null,
    "source": null,
    "clientType": "androidApp",
    "rating": 4,
    "originalRating": null,
    "reviewTitle": null,
    "reviewContent": "nice product but absorption boht kam hai rat rat main 3 diper change krny padty hain or iski outer layer leak ho jati hai... plz do something with its absorption ",
    "reviewTime": "07 Dec 2020",
    "zonedReviewTime": null,
    "likeCount": 0,
    "likeText": null,
    "isMeLike": null,
    "helpful": true,
    "rejected": false,
    "rejectionReason": null,
    "resubmissionTooltip": null,
    "resubmissionMessage": null,
    "qcReasonId": null,
    "qcDate": null,
    "isPurchased": true,
    "isGuest": false,
    "sellerId": 6005009103200,
    "sellerName": null,
    "boughtDate": "12 Nov 2020",
    "zonedBoughtDate": null,
    "reviewStatus": "approved",
    "qcTag": null,
    "qcScore": null,
    "isQced": false,
    "itemId": 171160358,
    "itemPic": "https://static-01.daraz.pk/p/6a6462c3a4cffb8b1cac5ea529f7dce4.jpg",
    "itemTitle": "BEBEM - Pack of 3 Baby diapers - Jumbo economy pack - Size 6 XXL - 44 Pcs ( 16+ kg ).",
    "itemUrl": "https://www.daraz.pk/bebem-pack-of-3-baby-diapers-jumbo-economy-pack-size-6-xxl-44-pcs-16-kg-i171160358-s1341700713.html",
    "originPrice": null,
    "salesPrice": null,
    "promotion": null,
    "skuInfo": "Size Diaper:XXL Size (14-25kg), Diaper Pack Size:44",
    "tags": null,
    "skuId": "1341700713",
    "configSku": "171160358_PK",
    "lastReviewer": "Iqbal, Muhammad AhmedIqbal, Muhammad Ahmed",
    "isReportable": 0,
    "reportStatus": null,
    "reportDate": null,
    "reportTimes": 0,
    "upVotes": 0,
    "downVotes": 0,
    "isExternal": 0,
    "replies": [],
    "canEdit": true,
    "images": null,
    "imageQCStatus": null,
    "submitInfo": {
      "os": "ios",
      "source": "myreview",
      "terminal": "weex",
      "network": "WIFI"
    },
    "imageHost": "//sg-live.slatic.net",
    "showUploader": true,
    "showVideoUploader": false,
    "relevanceScore": 40.0,
    "isCompleted": 1,
    "videoId": null,
    "isVideoReady": null,
    "videoCoverUrl": null,
    "avatar": null,
    "canDownloadImage": null,
    "targetId": 171160358,
    "targetType": "item"
  },
  {
    "reviewRateId": 10673228660358,
    "reviewType": "PRODUCT_REVIEW",
    "buyerId": 93384,
    "buyerName": "Noor M.",
    "buyerEmail": null,
    "realBuyerName": null,
    "isAnonymous": false,
    "tradeOrderId": null,
    "source": null,
    "clientType": "androidApp",
    "rating": 5,
    "originalRating": null,
    "reviewTitle": null,
    "reviewContent": "Very good quality, low cost and very well packaged. Promptly delivered next day. Seller recommended for purchase. Keep up the good work Daraz",
    "reviewTime": "16 Oct 2020",
    "zonedReviewTime": null,
    "likeCount": 0,
    "likeText": null,
    "isMeLike": null,
    "helpful": true,
    "rejected": false,
    "rejectionReason": null,
    "resubmissionTooltip": null,
    "resubmissionMessage": null,
    "qcReasonId": null,
    "qcDate": null,
    "isPurchased": true,
    "isGuest": false,
    "sellerId": 6005009103200,
    "sellerName": null,
    "boughtDate": "14 Oct 2020",
    "zonedBoughtDate": null,
    "reviewStatus": "approved",
    "qcTag": null,
    "qcScore": null,
    "isQced": false,
    "itemId": 171160358,
    "itemPic": "https://static-01.daraz.pk/p/6a6462c3a4cffb8b1cac5ea529f7dce4.jpg",
    "itemTitle": "BEBEM - Pack of 3 Baby diapers - Jumbo economy pack - Size 6 XXL - 44 Pcs ( 16+ kg ).",
    "itemUrl": "https://www.daraz.pk/bebem-pack-of-3-baby-diapers-jumbo-economy-pack-size-6-xxl-44-pcs-16-kg-i171160358-s1341700713.html",
    "originPrice": null,
    "salesPrice": null,
    "promotion": null,
    "skuInfo": "Size Diaper:XXL Size (14-25kg), Diaper Pack Size:44",
    "tags": null,
    "skuId": "1341700713",
    "configSku": "171160358_PK",
    "lastReviewer": "Iqbal, Muhammad AhmedIqbal, Muhammad Ahmed",
    "isReportable": 0,
    "reportStatus": null,
    "reportDate": null,
    "reportTimes": 0,
    "upVotes": 0,
    "downVotes": 0,
    "isExternal": 0,
    "replies": [],
    "canEdit": true,
    "images": null,
    "imageQCStatus": null,
    "submitInfo": {
      "os": "ios",
      "source": "myreview",
      "terminal": "weex",
      "network": "WIFI"
    },
    "imageHost": "//sg-live.slatic.net",
    "showUploader": true,
    "showVideoUploader": false,
    "relevanceScore": 40.0,
    "isCompleted": 1,
    "videoId": null,
    "isVideoReady": null,
    "videoCoverUrl": null,
    "avatar": null,
    "canDownloadImage": null,
    "targetId": 171160358,
    "targetType": "item"
  },
  {
    "reviewRateId": 11067211860358,
    "reviewType": "PRODUCT_REVIEW",
    "buyerId": 600000212750,
    "buyerName": "Dilshad A.",
    "buyerEmail": null,
    "realBuyerName": null,
    "isAnonymous": false,
    "tradeOrderId": null,
    "source": null,
    "clientType": "androidApp",
    "rating": 5,
    "originalRating": null,
    "reviewTitle": null,
    "reviewContent": "Quality wise good and economical product. Thnx to daraz for introducing such products",
    "reviewTime": "31 Oct 2020",
    "zonedReviewTime": null,
    "likeCount": 0,
    "likeText": null,
    "isMeLike": null,
    "helpful": true,
    "rejected": false,
    "rejectionReason": null,
    "resubmissionTooltip": null,
    "resubmissionMessage": null,
    "qcReasonId": null,
    "qcDate": null,
    "isPurchased": true,
    "isGuest": false,
    "sellerId": 6005009103200,
    "sellerName": null,
    "boughtDate": "23 Oct 2020",
    "zonedBoughtDate": null,
    "reviewStatus": "approved",
    "qcTag": null,
    "qcScore": null,
    "isQced": false,
    "itemId": 171160358,
    "itemPic": "https://static-01.daraz.pk/p/6a6462c3a4cffb8b1cac5ea529f7dce4.jpg",
    "itemTitle": "BEBEM - Pack of 3 Baby diapers - Jumbo economy pack - Size 6 XXL - 44 Pcs ( 16+ kg ).",
    "itemUrl": "https://www.daraz.pk/bebem-pack-of-3-baby-diapers-jumbo-economy-pack-size-6-xxl-44-pcs-16-kg-i171160358-s1341700713.html",
    "originPrice": null,
    "salesPrice": null,
    "promotion": null,
    "skuInfo": "Size Diaper:XXL Size (14-25kg), Diaper Pack Size:44",
    "tags": null,
    "skuId": "1341700713",
    "configSku": "171160358_PK",
    "lastReviewer": "Balani, RahulBalani, Rahul",
    "isReportable": 0,
    "reportStatus": null,
    "reportDate": null,
    "reportTimes": 0,
    "upVotes": 0,
    "downVotes": 0,
    "isExternal": 0,
    "replies": [],
    "canEdit": true,
    "images": null,
    "imageQCStatus": null,
    "submitInfo": {
      "os": "ios",
      "source": "myreview",
      "terminal": "weex",
      "network": "WIFI"
    },
    "imageHost": "//sg-live.slatic.net",
    "showUploader": true,
    "showVideoUploader": false,
    "relevanceScore": 38.88,
    "isCompleted": 1,
    "videoId": null,
    "isVideoReady": null,
    "videoCoverUrl": null,
    "avatar": null,
    "canDownloadImage": null,
    "targetId": 171160358,
    "targetType": "item"
  },
  {
    "reviewRateId": 12039293360358,
    "reviewType": "PRODUCT_REVIEW",
    "buyerId": 103462,
    "buyerName": "Waleed I.",
    "buyerEmail": null,
    "realBuyerName": null,
    "isAnonymous": false,
    "tradeOrderId": null,
    "source": null,
    "clientType": "androidApp",
    "rating": 5,
    "originalRating": null,
    "reviewTitle": null,
    "reviewContent": "i really like these diapers for my baby\n..very soft and convenient. . thanks daraz",
    "reviewTime": "18 Dec 2020",
    "zonedReviewTime": null,
    "likeCount": 0,
    "likeText": null,
    "isMeLike": null,
    "helpful": true,
    "rejected": false,
    "rejectionReason": null,
    "resubmissionTooltip": null,
    "resubmissionMessage": null,
    "qcReasonId": null,
    "qcDate": null,
    "isPurchased": true,
    "isGuest": false,
    "sellerId": 6005009103200,
    "sellerName": null,
    "boughtDate": "24 Nov 2020",
    "zonedBoughtDate": null,
    "reviewStatus": "approved",
    "qcTag": null,
    "qcScore": null,
    "isQced": false,
    "itemId": 171160358,
    "itemPic": "https://static-01.daraz.pk/p/6a6462c3a4cffb8b1cac5ea529f7dce4.jpg",
    "itemTitle": "BEBEM - Pack of 3 Baby diapers - Jumbo economy pack - Size 6 XXL - 44 Pcs ( 16+ kg ).",
    "itemUrl": "https://www.daraz.pk/bebem-pack-of-3-baby-diapers-jumbo-economy-pack-size-6-xxl-44-pcs-16-kg-i171160358-s1341700713.html",
    "originPrice": null,
    "salesPrice": null,
    "promotion": null,
    "skuInfo": "Size Diaper:XXL Size (14-25kg), Diaper Pack Size:44",
    "tags": null,
    "skuId": "1341700713",
    "configSku": "171160358_PK",
    "lastReviewer": "Naveed Malik, MustafaNaveed Malik, Mustafa",
    "isReportable": 0,
    "reportStatus": null,
    "reportDate": null,
    "reportTimes": 0,
    "upVotes": 0,
    "downVotes": 0,
    "isExternal": 0,
    "replies": [],
    "canEdit": true,
    "images": null,
    "imageQCStatus": null,
    "submitInfo": {
      "os": "ios",
      "source": "myreview",
      "terminal": "weex",
      "network": "WIFI"
    },
    "imageHost": "//sg-live.slatic.net",
    "showUploader": true,
    "showVideoUploader": false,
    "relevanceScore": 38.65,
    "isCompleted": 1,
    "videoId": null,
    "isVideoReady": null,
    "videoCoverUrl": null,
    "avatar": "https://static-01.daraz.pk/p/eb8699ffdc9d30452891c59f38781880.jpg",
    "canDownloadImage": null,
    "targetId": 171160358,
    "targetType": "item"
  },
  {
    "reviewRateId": 11964059760358,
    "reviewType": "PRODUCT_REVIEW",
    "buyerId": 805219,
    "buyerName": "abdul W.",
    "buyerEmail": null,
    "realBuyerName": null,
    "isAnonymous": false,
    "tradeOrderId": null,
    "source": null,
    "clientType": "androidApp",
    "rating": 5,
    "originalRating": null,
    "reviewTitle": null,
    "reviewContent": "good quality delivery on time recommend this seller,\ud83d\udc4d\ud83d\udc4d\ud83d\udc4d\ud83d\udc4d",
    "reviewTime": "27 Nov 2020",
    "zonedReviewTime": null,
    "likeCount": 0,
    "likeText": null,
    "isMeLike": null,
    "helpful": true,
    "rejected": false,
    "rejectionReason": null,
    "resubmissionTooltip": null,
    "resubmissionMessage": null,
    "qcReasonId": null,
    "qcDate": null,
    "isPurchased": true,
    "isGuest": false,
    "sellerId": 6005009103200,
    "sellerName": null,
    "boughtDate": "22 Nov 2020",
    "zonedBoughtDate": null,
    "reviewStatus": "approved",
    "qcTag": null,
    "qcScore": null,
    "isQced": false,
    "itemId": 171160358,
    "itemPic": "https://static-01.daraz.pk/p/6a6462c3a4cffb8b1cac5ea529f7dce4.jpg",
    "itemTitle": "BEBEM - Pack of 3 Baby diapers - Jumbo economy pack - Size 6 XXL - 44 Pcs ( 16+ kg ).",
    "itemUrl": "https://www.daraz.pk/bebem-pack-of-3-baby-diapers-jumbo-economy-pack-size-6-xxl-44-pcs-16-kg-i171160358-s1341700713.html",
    "originPrice": null,
    "salesPrice": null,
    "promotion": null,
    "skuInfo": "Size Diaper:XXL Size (14-25kg), Diaper Pack Size:44",
    "tags": null,
    "skuId": "1341700713",
    "configSku": "171160358_PK",
    "lastReviewer": "Khan, AyeshaKhan, Ayesha",
    "isReportable": 0,
    "reportStatus": null,
    "reportDate": null,
    "reportTimes": 0,
    "upVotes": 0,
    "downVotes": 0,
    "isExternal": 0,
    "replies": [],
    "canEdit": true,
    "images": null,
    "imageQCStatus": null,
    "submitInfo": {
      "os": "ios",
      "source": "myreview",
      "terminal": "weex",
      "network": "WIFI"
    },
    "imageHost": "//sg-live.slatic.net",
    "showUploader": true,
    "showVideoUploader": false,
    "relevanceScore": 37.0,
    "isCompleted": 1,
    "videoId": null,
    "isVideoReady": null,
    "videoCoverUrl": null,
    "avatar": null,
    "canDownloadImage": null,
    "targetId": 171160358,
    "targetType": "item"
  },
  {
    "reviewRateId": 17833605060358,
    "reviewType": "PRODUCT_REVIEW",
    "buyerId": 600006021046,
    "buyerName": "Abdur R.",
    "buyerEmail": null,
    "realBuyerName": null,
    "isAnonymous": false,
    "tradeOrderId": null,
    "source": null,
    "clientType": "androidApp",
    "rating": 3,
    "originalRating": null,
    "reviewTitle": null,
    "reviewContent": "old lot sent. the diapers are 2 year old manufactured.",
    "reviewTime": "18 Jun 2021",
    "zonedReviewTime": null,
    "likeCount": 0,
    "likeText": null,
    "isMeLike": null,
    "helpful": true,
    "rejected": false,
    "rejectionReason": null,
    "resubmissionTooltip": null,
    "resubmissionMessage": null,
    "qcReasonId": null,
    "qcDate": null,
    "isPurchased": true,
    "isGuest": false,
    "sellerId": 6005009103200,
    "sellerName": null,
    "boughtDate": "13 Jun 2021",
    "zonedBoughtDate": null,
    "reviewStatus": "approved",
    "qcTag": null,
    "qcScore": null,
    "isQced": false,
    "itemId": 171160358,
    "itemPic": "https://static-01.daraz.pk/p/a769833298a7eabb9b49689c3dadb286.jpg",
    "itemTitle": "BEBEM - Pack of 3 Baby diapers - Jumbo economy pack - Size 6 XXL - 44 Pcs ( 16+ kg ).",
    "itemUrl": "https://www.daraz.pk/bebem-pack-of-3-baby-diapers-jumbo-economy-pack-size-6-xxl-44-pcs-16-kg-i171160358-s1341700713.html",
    "originPrice": null,
    "salesPrice": null,
    "promotion": null,
    "skuInfo": "Size Diaper:XXL Size (14-25kg), Diaper Pack Size:44",
    "tags": null,
    "skuId": "1341700713",
    "configSku": "171160358_PK",
    "lastReviewer": "Farooq, ArfeenFarooq, Arfeen",
    "isReportable": 0,
    "reportStatus": null,
    "reportDate": null,
    "reportTimes": 0,
    "upVotes": 0,
    "downVotes": 0,
    "isExternal": 0,
    "replies": [],
    "canEdit": true,
    "images": null,
    "imageQCStatus": null,
    "submitInfo": {
      "os": "ios",
      "source": "myreview",
      "terminal": "weex",
      "network": "WIFI"
    },
    "imageHost": "//sg-live.slatic.net",
    "showUploader": true,
    "showVideoUploader": false,
    "relevanceScore": 36.55,
    "isCompleted": 1,
    "videoId": null,
    "isVideoReady": null,
    "videoCoverUrl": null,
    "avatar": null,
    "canDownloadImage": null,
    "targetId": 171160358,
    "targetType": "item"
  },
  {
    "reviewRateId": 12041477660358,
    "reviewType": "PRODUCT_REVIEW",
    "buyerId": 3351429,
    "buyerName": "Kamran R.",
    "buyerEmail": null,
    "realBuyerName": null,
    "isAnonymous": false,
    "tradeOrderId": null,
    "source": null,
    "clientType": "androidApp",
    "rating": 5,
    "originalRating": null,
    "reviewTitle": null,
    "reviewContent": "100% recommended. good pakage and timely delivery. ",
    "reviewTime": "08 Dec 2020",
    "zonedReviewTime": null,
    "likeCount": 0,
    "likeText": null,
    "isMeLike": null,
    "helpful": true,
    "rejected": false,
    "rejectionReason": null,
    "resubmissionTooltip": null,
    "resubmissionMessage": null,
    "qcReasonId": null,
    "qcDate": null,
    "isPurchased": true,
    "isGuest": false,
    "sellerId": 6005009103200,
    "sellerName": null,
    "boughtDate": "25 Nov 2020",
    "zonedBoughtDate": null,
    "reviewStatus": "approved",
    "qcTag": null,
    "qcScore": null,
    "isQced": false,
    "itemId": 171160358,
    "itemPic": "https://static-01.daraz.pk/p/6a6462c3a4cffb8b1cac5ea529f7dce4.jpg",
    "itemTitle": "BEBEM - Pack of 3 Baby diapers - Jumbo economy pack - Size 6 XXL - 44 Pcs ( 16+ kg ).",
    "itemUrl": "https://www.daraz.pk/bebem-pack-of-3-baby-diapers-jumbo-economy-pack-size-6-xxl-44-pcs-16-kg-i171160358-s1341700713.html",
    "originPrice": null,
    "salesPrice": null,
    "promotion": null,
    "skuInfo": "Size Diaper:XXL Size (14-25kg), Diaper Pack Size:44",
    "tags": null,
    "skuId": "1341700713",
    "configSku": "171160358_PK",
    "lastReviewer": "Khan, AyeshaKhan, Ayesha",
    "isReportable": 0,
    "reportStatus": null,
    "reportDate": null,
    "reportTimes": 0,
    "upVotes": 0,
    "downVotes": 0,
    "isExternal": 0,
    "replies": [],
    "canEdit": true,
    "images": null,
    "imageQCStatus": null,
    "submitInfo": {
      "os": "ios",
      "source": "myreview",
      "terminal": "weex",
      "network": "WIFI"
    },
    "imageHost": "//sg-live.slatic.net",
    "showUploader": true,
    "showVideoUploader": false,
    "relevanceScore": 36.33,
    "isCompleted": 1,
    "videoId": null,
    "isVideoReady": null,
    "videoCoverUrl": null,
    "avatar": "https://graph.facebook.com/10214040388317847/picture",
    "canDownloadImage": null,
    "targetId": 171160358,
    "targetType": "item"
  },
  {
    "reviewRateId": 14021870460358,
    "reviewType": "PRODUCT_REVIEW",
    "buyerId": 600015393090,
    "buyerName": "prince O.",
    "buyerEmail": null,
    "realBuyerName": null,
    "isAnonymous": false,
    "tradeOrderId": null,
    "source": null,
    "clientType": "androidApp",
    "rating": 5,
    "originalRating": null,
    "reviewTitle": null,
    "reviewContent": "zabardast diapers hain well packed thanks daraz",
    "reviewTime": "24 Apr 2021",
    "zonedReviewTime": null,
    "likeCount": 0,
    "likeText": null,
    "isMeLike": null,
    "helpful": true,
    "rejected": false,
    "rejectionReason": null,
    "resubmissionTooltip": null,
    "resubmissionMessage": null,
    "qcReasonId": null,
    "qcDate": null,
    "isPurchased": true,
    "isGuest": false,
    "sellerId": 6005009103200,
    "sellerName": null,
    "boughtDate": "05 Feb 2021",
    "zonedBoughtDate": null,
    "reviewStatus": "approved",
    "qcTag": null,
    "qcScore": null,
    "isQced": false,
    "itemId": 171160358,
    "itemPic": "https://static-01.daraz.pk/p/6a6462c3a4cffb8b1cac5ea529f7dce4.jpg",
    "itemTitle": "BEBEM - Pack of 3 Baby diapers - Jumbo economy pack - Size 6 XXL - 44 Pcs ( 16+ kg ).",
    "itemUrl": "https://www.daraz.pk/bebem-pack-of-3-baby-diapers-jumbo-economy-pack-size-6-xxl-44-pcs-16-kg-i171160358-s1341700713.html",
    "originPrice": null,
    "salesPrice": null,
    "promotion": null,
    "skuInfo": "Size Diaper:XXL Size (14-25kg), Diaper Pack Size:44",
    "tags": null,
    "skuId": "1341700713",
    "configSku": "171160358_PK",
    "lastReviewer": "Farooq, ArfeenFarooq, Arfeen",
    "isReportable": 0,
    "reportStatus": null,
    "reportDate": null,
    "reportTimes": 0,
    "upVotes": 0,
    "downVotes": 0,
    "isExternal": 0,
    "replies": [],
    "canEdit": true,
    "images": null,
    "imageQCStatus": null,
    "submitInfo": {
      "os": "ios",
      "source": "myreview",
      "terminal": "weex",
      "network": "WIFI"
    },
    "imageHost": "//sg-live.slatic.net",
    "showUploader": true,
    "showVideoUploader": false,
    "relevanceScore": 36.03,
    "isCompleted": 1,
    "videoId": null,
    "isVideoReady": null,
    "videoCoverUrl": null,
    "avatar": null,
    "canDownloadImage": null,
    "targetId": 171160358,
    "targetType": "item"
  },
  {
    "reviewRateId": 14061020560358,
    "reviewType": "PRODUCT_REVIEW",
    "buyerId": 535306,
    "buyerName": "Junaid A.",
    "buyerEmail": null,
    "realBuyerName": null,
    "isAnonymous": false,
    "tradeOrderId": null,
    "source": null,
    "clientType": "androidApp",
    "rating": 5,
    "originalRating": null,
    "reviewTitle": null,
    "reviewContent": "nice experience, value for money. good job",
    "reviewTime": "09 Mar 2021",
    "zonedReviewTime": null,
    "likeCount": 0,
    "likeText": null,
    "isMeLike": null,
    "helpful": true,
    "rejected": false,
    "rejectionReason": null,
    "resubmissionTooltip": null,
    "resubmissionMessage": null,
    "qcReasonId": null,
    "qcDate": null,
    "isPurchased": true,
    "isGuest": false,
    "sellerId": 6005009103200,
    "sellerName": null,
    "boughtDate": "08 Feb 2021",
    "zonedBoughtDate": null,
    "reviewStatus": "approved",
    "qcTag": null,
    "qcScore": null,
    "isQced": false,
    "itemId": 171160358,
    "itemPic": "https://static-01.daraz.pk/p/6a6462c3a4cffb8b1cac5ea529f7dce4.jpg",
    "itemTitle": "BEBEM - Pack of 3 Baby diapers - Jumbo economy pack - Size 6 XXL - 44 Pcs ( 16+ kg ).",
    "itemUrl": "https://www.daraz.pk/bebem-pack-of-3-baby-diapers-jumbo-economy-pack-size-6-xxl-44-pcs-16-kg-i171160358-s1341700713.html",
    "originPrice": null,
    "salesPrice": null,
    "promotion": null,
    "skuInfo": "Size Diaper:XXL Size (14-25kg), Diaper Pack Size:44",
    "tags": null,
    "skuId": "1341700713",
    "configSku": "171160358_PK",
    "lastReviewer": "Farooq, ArfeenFarooq, Arfeen",
    "isReportable": 0,
    "reportStatus": null,
    "reportDate": null,
    "reportTimes": 0,
    "upVotes": 0,
    "downVotes": 0,
    "isExternal": 0,
    "replies": [],
    "canEdit": true,
    "images": null,
    "imageQCStatus": null,
    "submitInfo": {
      "os": "ios",
      "source": "myreview",
      "terminal": "weex",
      "network": "WIFI"
    },
    "imageHost": "//sg-live.slatic.net",
    "showUploader": true,
    "showVideoUploader": false,
    "relevanceScore": 35.65,
    "isCompleted": 1,
    "videoId": null,
    "isVideoReady": null,
    "videoCoverUrl": null,
    "avatar": "https://graph.facebook.com/10157458824794018/picture",
    "canDownloadImage": null,
    "targetId": 171160358,
    "targetType": "item"
  },
  {
    "reviewRateId": 11847442760358,
    "reviewType": "PRODUCT_REVIEW",
    "buyerId": 3858837,
    "buyerName": "Badar U.",
    "buyerEmail": null,
    "realBuyerName": null,
    "isAnonymous": false,
    "tradeOrderId": null,
    "source": null,
    "clientType": "androidApp",
    "rating": 5,
    "originalRating": null,
    "reviewTitle": null,
    "reviewContent": "Seller recommended received as described\n",
    "reviewTime": "22 Nov 2020",
    "zonedReviewTime": null,
    "likeCount": 0,
    "likeText": null,
    "isMeLike": null,
    "helpful": true,
    "rejected": false,
    "rejectionReason": null,
    "resubmissionTooltip": null,
    "resubmissionMessage": null,
    "qcReasonId": null,
    "qcDate": null,
    "isPurchased": true,
    "isGuest": false,
    "sellerId": 6005009103200,
    "sellerName": null,
    "boughtDate": "17 Nov 2020",
    "zonedBoughtDate": null,
    "reviewStatus": "approved",
    "qcTag": null,
    "qcScore": null,
    "isQced": false,
    "itemId": 171160358,
    "itemPic": "https://static-01.daraz.pk/p/6a6462c3a4cffb8b1cac5ea529f7dce4.jpg",
    "itemTitle": "BEBEM - Pack of 3 Baby diapers - Jumbo economy pack - Size 6 XXL - 44 Pcs ( 16+ kg ).",
    "itemUrl": "https://www.daraz.pk/bebem-pack-of-3-baby-diapers-jumbo-economy-pack-size-6-xxl-44-pcs-16-kg-i171160358-s1341700713.html",
    "originPrice": null,
    "salesPrice": null,
    "promotion": null,
    "skuInfo": "Size Diaper:XXL Size (14-25kg), Diaper Pack Size:44",
    "tags": null,
    "skuId": "1341700713",
    "configSku": "171160358_PK",
    "lastReviewer": "Khan, AyeshaKhan, Ayesha",
    "isReportable": 0,
    "reportStatus": null,
    "reportDate": null,
    "reportTimes": 0,
    "upVotes": 0,
    "downVotes": 0,
    "isExternal": 0,
    "replies": [],
    "canEdit": true,
    "images": null,
    "imageQCStatus": null,
    "submitInfo": {
      "os": "ios",
      "source": "myreview",
      "terminal": "weex",
      "network": "4G"
    },
    "imageHost": "//sg-live.slatic.net",
    "showUploader": true,
    "showVideoUploader": false,
    "relevanceScore": 35.58,
    "isCompleted": 1,
    "videoId": null,
    "isVideoReady": null,
    "videoCoverUrl": null,
    "avatar": null,
    "canDownloadImage": null,
    "targetId": 171160358,
    "targetType": "item"
  },
  {
    "reviewRateId": 16809030560358,
    "reviewType": "PRODUCT_REVIEW",
    "buyerId": 958416,
    "buyerName": "Osama H.",
    "buyerEmail": null,
    "realBuyerName": null,
    "isAnonymous": false,
    "tradeOrderId": null,
    "source": null,
    "clientType": "androidApp",
    "rating": 5,
    "originalRating": null,
    "reviewTitle": null,
    "reviewContent": "Good quality and value to money product\n",
    "reviewTime": "31 May 2021",
    "zonedReviewTime": null,
    "likeCount": 0,
    "likeText": null,
    "isMeLike": null,
    "helpful": true,
    "rejected": false,
    "rejectionReason": null,
    "resubmissionTooltip": null,
    "resubmissionMessage": null,
    "qcReasonId": null,
    "qcDate": null,
    "isPurchased": true,
    "isGuest": false,
    "sellerId": 6005009103200,
    "sellerName": null,
    "boughtDate": "15 May 2021",
    "zonedBoughtDate": null,
    "reviewStatus": "approved",
    "qcTag": null,
    "qcScore": null,
    "isQced": false,
    "itemId": 171160358,
    "itemPic": "https://static-01.daraz.pk/p/a769833298a7eabb9b49689c3dadb286.jpg",
    "itemTitle": "BEBEM - Pack of 3 Baby diapers - Jumbo economy pack - Size 6 XXL - 44 Pcs ( 16+ kg ).",
    "itemUrl": "https://www.daraz.pk/bebem-pack-of-3-baby-diapers-jumbo-economy-pack-size-6-xxl-44-pcs-16-kg-i171160358-s1341700713.html",
    "originPrice": null,
    "salesPrice": null,
    "promotion": null,
    "skuInfo": "Size Diaper:XXL Size (14-25kg), Diaper Pack Size:44",
    "tags": null,
    "skuId": "1341700713",
    "configSku": "171160358_PK",
    "lastReviewer": "Farooq, ArfeenFarooq, Arfeen",
    "isReportable": 0,
    "reportStatus": null,
    "reportDate": null,
    "reportTimes": 0,
    "upVotes": 0,
    "downVotes": 0,
    "isExternal": 0,
    "replies": [],
    "canEdit": true,
    "images": null,
    "imageQCStatus": null,
    "submitInfo": {
      "os": "ios",
      "source": "myreview",
      "terminal": "msite",
      "network": "4G"
    },
    "imageHost": "//sg-live.slatic.net",
    "showUploader": true,
    "showVideoUploader": false,
    "relevanceScore": 35.5,
    "isCompleted": 1,
    "videoId": null,
    "isVideoReady": null,
    "videoCoverUrl": null,
    "avatar": "https://graph.facebook.com/10156339379440380/picture",
    "canDownloadImage": null,
    "targetId": 171160358,
    "targetType": "item"
  },
  {
    "reviewRateId": 10959066560358,
    "reviewType": "PRODUCT_REVIEW",
    "buyerId": 600001894929,
    "buyerName": "Umme B.",
    "buyerEmail": null,
    "realBuyerName": null,
    "isAnonymous": false,
    "tradeOrderId": null,
    "source": null,
    "clientType": "androidApp",
    "rating": 5,
    "originalRating": null,
    "reviewTitle": null,
    "reviewContent": "bohat achy daipers hain bht low price me",
    "reviewTime": "12 Nov 2020",
    "zonedReviewTime": null,
    "likeCount": 0,
    "likeText": null,
    "isMeLike": null,
    "helpful": true,
    "rejected": false,
    "rejectionReason": null,
    "resubmissionTooltip": null,
    "resubmissionMessage": null,
    "qcReasonId": null,
    "qcDate": null,
    "isPurchased": true,
    "isGuest": false,
    "sellerId": 6005009103200,
    "sellerName": null,
    "boughtDate": "20 Oct 2020",
    "zonedBoughtDate": null,
    "reviewStatus": "approved",
    "qcTag": null,
    "qcScore": null,
    "isQced": false,
    "itemId": 171160358,
    "itemPic": "https://static-01.daraz.pk/p/6a6462c3a4cffb8b1cac5ea529f7dce4.jpg",
    "itemTitle": "BEBEM - Pack of 3 Baby diapers - Jumbo economy pack - Size 6 XXL - 44 Pcs ( 16+ kg ).",
    "itemUrl": "https://www.daraz.pk/bebem-pack-of-3-baby-diapers-jumbo-economy-pack-size-6-xxl-44-pcs-16-kg-i171160358-s1341700713.html",
    "originPrice": null,
    "salesPrice": null,
    "promotion": null,
    "skuInfo": "Size Diaper:XXL Size (14-25kg), Diaper Pack Size:44",
    "tags": null,
    "skuId": "1341700713",
    "configSku": "171160358_PK",
    "lastReviewer": "Khan, AyeshaKhan, Ayesha",
    "isReportable": 0,
    "reportStatus": null,
    "reportDate": null,
    "reportTimes": 0,
    "upVotes": 0,
    "downVotes": 0,
    "isExternal": 0,
    "replies": [],
    "canEdit": true,
    "images": null,
    "imageQCStatus": null,
    "submitInfo": {
      "os": "ios",
      "source": "myreview",
      "terminal": "weex",
      "network": "WIFI"
    },
    "imageHost": "//sg-live.slatic.net",
    "showUploader": true,
    "showVideoUploader": false,
    "relevanceScore": 35.5,
    "isCompleted": 1,
    "videoId": null,
    "isVideoReady": null,
    "videoCoverUrl": null,
    "avatar": "https://graph.facebook.com/2188800931172495/picture",
    "canDownloadImage": null,
    "targetId": 171160358,
    "targetType": "item"
  },
  {
    "reviewRateId": 12253425260358,
    "reviewType": "PRODUCT_REVIEW",
    "buyerId": 600026430877,
    "buyerName": "zayyan A.",
    "buyerEmail": null,
    "realBuyerName": null,
    "isAnonymous": false,
    "tradeOrderId": null,
    "source": null,
    "clientType": "androidApp",
    "rating": 5,
    "originalRating": null,
    "reviewTitle": null,
    "reviewContent": "best quality and price!!! thank youuuuu",
    "reviewTime": "26 Dec 2020",
    "zonedReviewTime": null,
    "likeCount": 0,
    "likeText": null,
    "isMeLike": null,
    "helpful": true,
    "rejected": false,
    "rejectionReason": null,
    "resubmissionTooltip": null,
    "resubmissionMessage": null,
    "qcReasonId": null,
    "qcDate": null,
    "isPurchased": true,
    "isGuest": false,
    "sellerId": 6005009103200,
    "sellerName": null,
    "boughtDate": "04 Dec 2020",
    "zonedBoughtDate": null,
    "reviewStatus": "approved",
    "qcTag": null,
    "qcScore": null,
    "isQced": false,
    "itemId": 171160358,
    "itemPic": "https://static-01.daraz.pk/p/6a6462c3a4cffb8b1cac5ea529f7dce4.jpg",
    "itemTitle": "BEBEM - Pack of 3 Baby diapers - Jumbo economy pack - Size 6 XXL - 44 Pcs ( 16+ kg ).",
    "itemUrl": "https://www.daraz.pk/bebem-pack-of-3-baby-diapers-jumbo-economy-pack-size-6-xxl-44-pcs-16-kg-i171160358-s1341700713.html",
    "originPrice": null,
    "salesPrice": null,
    "promotion": null,
    "skuInfo": "Size Diaper:XXL Size (14-25kg), Diaper Pack Size:44",
    "tags": null,
    "skuId": "1341700713",
    "configSku": "171160358_PK",
    "lastReviewer": "Naveed Malik, MustafaNaveed Malik, Mustafa",
    "isReportable": 0,
    "reportStatus": null,
    "reportDate": null,
    "reportTimes": 0,
    "upVotes": 0,
    "downVotes": 0,
    "isExternal": 0,
    "replies": [],
    "canEdit": true,
    "images": null,
    "imageQCStatus": null,
    "submitInfo": {
      "os": "ios",
      "source": "order_detail",
      "terminal": "weex",
      "network": "4G"
    },
    "imageHost": "//sg-live.slatic.net",
    "showUploader": true,
    "showVideoUploader": false,
    "relevanceScore": 35.43,
    "isCompleted": 1,
    "videoId": null,
    "isVideoReady": null,
    "videoCoverUrl": null,
    "avatar": null,
    "canDownloadImage": null,
    "targetId": 171160358,
    "targetType": "item"
  },
  {
    "reviewRateId": 11706272860358,
    "reviewType": "PRODUCT_REVIEW",
    "buyerId": 763434,
    "buyerName": "Ghulam H.",
    "buyerEmail": null,
    "realBuyerName": null,
    "isAnonymous": false,
    "tradeOrderId": null,
    "source": null,
    "clientType": "androidApp",
    "rating": 5,
    "originalRating": null,
    "reviewTitle": null,
    "reviewContent": "Vip packing i recommended this seller ",
    "reviewTime": "19 Nov 2020",
    "zonedReviewTime": null,
    "likeCount": 0,
    "likeText": null,
    "isMeLike": null,
    "helpful": true,
    "rejected": false,
    "rejectionReason": null,
    "resubmissionTooltip": null,
    "resubmissionMessage": null,
    "qcReasonId": null,
    "qcDate": null,
    "isPurchased": true,
    "isGuest": false,
    "sellerId": 6005009103200,
    "sellerName": null,
    "boughtDate": "16 Nov 2020",
    "zonedBoughtDate": null,
    "reviewStatus": "approved",
    "qcTag": null,
    "qcScore": null,
    "isQced": false,
    "itemId": 171160358,
    "itemPic": "https://static-01.daraz.pk/p/6a6462c3a4cffb8b1cac5ea529f7dce4.jpg",
    "itemTitle": "BEBEM - Pack of 3 Baby diapers - Jumbo economy pack - Size 6 XXL - 44 Pcs ( 16+ kg ).",
    "itemUrl": "https://www.daraz.pk/bebem-pack-of-3-baby-diapers-jumbo-economy-pack-size-6-xxl-44-pcs-16-kg-i171160358-s1341700713.html",
    "originPrice": null,
    "salesPrice": null,
    "promotion": null,
    "skuInfo": "Size Diaper:XXL Size (14-25kg), Diaper Pack Size:44",
    "tags": null,
    "skuId": "1341700713",
    "configSku": "171160358_PK",
    "lastReviewer": "Balani, RahulBalani, Rahul",
    "isReportable": 0,
    "reportStatus": null,
    "reportDate": null,
    "reportTimes": 0,
    "upVotes": 0,
    "downVotes": 0,
    "isExternal": 0,
    "replies": [],
    "canEdit": true,
    "images": null,
    "imageQCStatus": null,
    "submitInfo": {
      "os": "ios",
      "source": "order_detail",
      "terminal": "weex",
      "network": "UNKNOWN"
    },
    "imageHost": "//sg-live.slatic.net",
    "showUploader": true,
    "showVideoUploader": false,
    "relevanceScore": 35.35,
    "isCompleted": 1,
    "videoId": null,
    "isVideoReady": null,
    "videoCoverUrl": null,
    "avatar": null,
    "canDownloadImage": null,
    "targetId": 171160358,
    "targetType": "item"
  },
  {
    "reviewRateId": 15120808060358,
    "reviewType": "PRODUCT_REVIEW",
    "buyerId": 2738114,
    "buyerName": "M***.",
    "buyerEmail": null,
    "realBuyerName": null,
    "isAnonymous": true,
    "tradeOrderId": null,
    "source": null,
    "clientType": "androidApp",
    "rating": 5,
    "originalRating": null,
    "reviewTitle": null,
    "reviewContent": "best product my baby is happy with it",
    "reviewTime": "31 Mar 2021",
    "zonedReviewTime": null,
    "likeCount": 0,
    "likeText": null,
    "isMeLike": null,
    "helpful": true,
    "rejected": false,
    "rejectionReason": null,
    "resubmissionTooltip": null,
    "resubmissionMessage": null,
    "qcReasonId": null,
    "qcDate": null,
    "isPurchased": true,
    "isGuest": false,
    "sellerId": 6005009103200,
    "sellerName": null,
    "boughtDate": "21 Mar 2021",
    "zonedBoughtDate": null,
    "reviewStatus": "approved",
    "qcTag": null,
    "qcScore": null,
    "isQced": false,
    "itemId": 171160358,
    "itemPic": "https://static-01.daraz.pk/p/a769833298a7eabb9b49689c3dadb286.jpg",
    "itemTitle": "BEBEM - Pack of 3 Baby diapers - Jumbo economy pack - Size 6 XXL - 44 Pcs ( 16+ kg ).",
    "itemUrl": "https://www.daraz.pk/bebem-pack-of-3-baby-diapers-jumbo-economy-pack-size-6-xxl-44-pcs-16-kg-i171160358-s1341700713.html",
    "originPrice": null,
    "salesPrice": null,
    "promotion": null,
    "skuInfo": "Size Diaper:XXL Size (14-25kg), Diaper Pack Size:44",
    "tags": null,
    "skuId": "1341700713",
    "configSku": "171160358_PK",
    "lastReviewer": "Naveed Malik, MustafaNaveed Malik, Mustafa",
    "isReportable": 0,
    "reportStatus": null,
    "reportDate": null,
    "reportTimes": 0,
    "upVotes": 0,
    "downVotes": 0,
    "isExternal": 0,
    "replies": [],
    "canEdit": true,
    "images": null,
    "imageQCStatus": null,
    "submitInfo": {
      "os": "ios",
      "source": "myreview",
      "terminal": "weex",
      "network": "WIFI"
    },
    "imageHost": "//sg-live.slatic.net",
    "showUploader": true,
    "showVideoUploader": false,
    "relevanceScore": 35.28,
    "isCompleted": 1,
    "videoId": null,
    "isVideoReady": null,
    "videoCoverUrl": null,
    "avatar": null,
    "canDownloadImage": null,
    "targetId": 171160358,
    "targetType": "item"
  },
  {
    "reviewRateId": 11633637960358,
    "reviewType": "PRODUCT_REVIEW",
    "buyerId": 600025221556,
    "buyerName": "mrs U.",
    "buyerEmail": null,
    "realBuyerName": null,
    "isAnonymous": false,
    "tradeOrderId": null,
    "source": null,
    "clientType": "androidApp",
    "rating": 5,
    "originalRating": null,
    "reviewTitle": null,
    "reviewContent": "plz dont increase price day by day. ",
    "reviewTime": "21 Dec 2020",
    "zonedReviewTime": null,
    "likeCount": 0,
    "likeText": null,
    "isMeLike": null,
    "helpful": true,
    "rejected": false,
    "rejectionReason": null,
    "resubmissionTooltip": null,
    "resubmissionMessage": null,
    "qcReasonId": null,
    "qcDate": null,
    "isPurchased": true,
    "isGuest": false,
    "sellerId": 6005009103200,
    "sellerName": null,
    "boughtDate": "13 Nov 2020",
    "zonedBoughtDate": null,
    "reviewStatus": "approved",
    "qcTag": null,
    "qcScore": null,
    "isQced": false,
    "itemId": 171160358,
    "itemPic": "https://static-01.daraz.pk/p/6a6462c3a4cffb8b1cac5ea529f7dce4.jpg",
    "itemTitle": "BEBEM - Pack of 3 Baby diapers - Jumbo economy pack - Size 6 XXL - 44 Pcs ( 16+ kg ).",
    "itemUrl": "https://www.daraz.pk/bebem-pack-of-3-baby-diapers-jumbo-economy-pack-size-6-xxl-44-pcs-16-kg-i171160358-s1341700713.html",
    "originPrice": null,
    "salesPrice": null,
    "promotion": null,
    "skuInfo": "Size Diaper:XXL Size (14-25kg), Diaper Pack Size:44",
    "tags": null,
    "skuId": "1341700713",
    "configSku": "171160358_PK",
    "lastReviewer": "Shahkar, UmerShahkar, Umer",
    "isReportable": 0,
    "reportStatus": null,
    "reportDate": null,
    "reportTimes": 0,
    "upVotes": 0,
    "downVotes": 0,
    "isExternal": 0,
    "replies": [],
    "canEdit": true,
    "images": null,
    "imageQCStatus": null,
    "submitInfo": {
      "os": "ios",
      "source": "myreview",
      "terminal": "weex",
      "network": "WIFI"
    },
    "imageHost": "//sg-live.slatic.net",
    "showUploader": true,
    "showVideoUploader": false,
    "relevanceScore": 35.2,
    "isCompleted": 1,
    "videoId": null,
    "isVideoReady": null,
    "videoCoverUrl": null,
    "avatar": null,
    "canDownloadImage": null,
    "targetId": 171160358,
    "targetType": "item"
  },
  {
    "reviewRateId": 11969683260358,
    "reviewType": "PRODUCT_REVIEW",
    "buyerId": 600025221556,
    "buyerName": "mrs U.",
    "buyerEmail": null,
    "realBuyerName": null,
    "isAnonymous": false,
    "tradeOrderId": null,
    "source": null,
    "clientType": "androidApp",
    "rating": 5,
    "originalRating": null,
    "reviewTitle": null,
    "reviewContent": "always satisfied alhumdulliAllah",
    "reviewTime": "21 Dec 2020",
    "zonedReviewTime": null,
    "likeCount": 0,
    "likeText": null,
    "isMeLike": null,
    "helpful": true,
    "rejected": false,
    "rejectionReason": null,
    "resubmissionTooltip": null,
    "resubmissionMessage": null,
    "qcReasonId": null,
    "qcDate": null,
    "isPurchased": true,
    "isGuest": false,
    "sellerId": 6005009103200,
    "sellerName": null,
    "boughtDate": "22 Nov 2020",
    "zonedBoughtDate": null,
    "reviewStatus": "approved",
    "qcTag": null,
    "qcScore": null,
    "isQced": false,
    "itemId": 171160358,
    "itemPic": "https://static-01.daraz.pk/p/6a6462c3a4cffb8b1cac5ea529f7dce4.jpg",
    "itemTitle": "BEBEM - Pack of 3 Baby diapers - Jumbo economy pack - Size 6 XXL - 44 Pcs ( 16+ kg ).",
    "itemUrl": "https://www.daraz.pk/bebem-pack-of-3-baby-diapers-jumbo-economy-pack-size-6-xxl-44-pcs-16-kg-i171160358-s1341700713.html",
    "originPrice": null,
    "salesPrice": null,
    "promotion": null,
    "skuInfo": "Size Diaper:XXL Size (14-25kg), Diaper Pack Size:44",
    "tags": null,
    "skuId": "1341700713",
    "configSku": "171160358_PK",
    "lastReviewer": "Shahkar, UmerShahkar, Umer",
    "isReportable": 0,
    "reportStatus": null,
    "reportDate": null,
    "reportTimes": 0,
    "upVotes": 0,
    "downVotes": 0,
    "isExternal": 0,
    "replies": [],
    "canEdit": true,
    "images": null,
    "imageQCStatus": null,
    "submitInfo": {
      "os": "ios",
      "source": "myreview",
      "terminal": "weex",
      "network": "WIFI"
    },
    "imageHost": "//sg-live.slatic.net",
    "showUploader": true,
    "showVideoUploader": false,
    "relevanceScore": 34.9,
    "isCompleted": 1,
    "videoId": null,
    "isVideoReady": null,
    "videoCoverUrl": null,
    "avatar": null,
    "canDownloadImage": null,
    "targetId": 171160358,
    "targetType": "item"
  },
  {
    "reviewRateId": 11557211960358,
    "reviewType": "PRODUCT_REVIEW",
    "buyerId": 180620,
    "buyerName": "Adnan Y.",
    "buyerEmail": null,
    "realBuyerName": null,
    "isAnonymous": false,
    "tradeOrderId": null,
    "source": null,
    "clientType": "androidApp",
    "rating": 5,
    "originalRating": null,
    "reviewTitle": null,
    "reviewContent": "good quality at reasonable price",
    "reviewTime": "13 Dec 2020",
    "zonedReviewTime": null,
    "likeCount": 0,
    "likeText": null,
    "isMeLike": null,
    "helpful": true,
    "rejected": false,
    "rejectionReason": null,
    "resubmissionTooltip": null,
    "resubmissionMessage": null,
    "qcReasonId": null,
    "qcDate": null,
    "isPurchased": true,
    "isGuest": false,
    "sellerId": 6005009103200,
    "sellerName": null,
    "boughtDate": "11 Nov 2020",
    "zonedBoughtDate": null,
    "reviewStatus": "approved",
    "qcTag": null,
    "qcScore": null,
    "isQced": false,
    "itemId": 171160358,
    "itemPic": "https://static-01.daraz.pk/p/6a6462c3a4cffb8b1cac5ea529f7dce4.jpg",
    "itemTitle": "BEBEM - Pack of 3 Baby diapers - Jumbo economy pack - Size 6 XXL - 44 Pcs ( 16+ kg ).",
    "itemUrl": "https://www.daraz.pk/bebem-pack-of-3-baby-diapers-jumbo-economy-pack-size-6-xxl-44-pcs-16-kg-i171160358-s1341700713.html",
    "originPrice": null,
    "salesPrice": null,
    "promotion": null,
    "skuInfo": "Size Diaper:XXL Size (14-25kg), Diaper Pack Size:44",
    "tags": null,
    "skuId": "1341700713",
    "configSku": "171160358_PK",
    "lastReviewer": "Khan, AyeshaKhan, Ayesha",
    "isReportable": 0,
    "reportStatus": null,
    "reportDate": null,
    "reportTimes": 0,
    "upVotes": 0,
    "downVotes": 0,
    "isExternal": 0,
    "replies": [],
    "canEdit": true,
    "images": null,
    "imageQCStatus": null,
    "submitInfo": {
      "os": "ios",
      "source": "myreview",
      "terminal": "weex",
      "network": "WIFI"
    },
    "imageHost": "//sg-live.slatic.net",
    "showUploader": true,
    "showVideoUploader": false,
    "relevanceScore": 34.9,
    "isCompleted": 1,
    "videoId": null,
    "isVideoReady": null,
    "videoCoverUrl": null,
    "avatar": "https://lh6.googleusercontent.com/-4XydIMA2ur8/AAAAAAAAAAI/AAAAAAAAAJM/kxFgOqx9Vm0/s96-c/photo.jpg",
    "canDownloadImage": null,
    "targetId": 171160358,
    "targetType": "item"
  },
  {
    "reviewRateId": 15012854060358,
    "reviewType": "PRODUCT_REVIEW",
    "buyerId": 600029445772,
    "buyerName": "Tayyaba A.",
    "buyerEmail": null,
    "realBuyerName": null,
    "isAnonymous": false,
    "tradeOrderId": null,
    "source": null,
    "clientType": "androidApp",
    "rating": 5,
    "originalRating": null,
    "reviewTitle": null,
    "reviewContent": "I am satisfied ",
    "reviewTime": "23 Mar 2021",
    "zonedReviewTime": null,
    "likeCount": 0,
    "likeText": null,
    "isMeLike": null,
    "helpful": true,
    "rejected": false,
    "rejectionReason": null,
    "resubmissionTooltip": null,
    "resubmissionMessage": null,
    "qcReasonId": null,
    "qcDate": null,
    "isPurchased": true,
    "isGuest": false,
    "sellerId": 6005009103200,
    "sellerName": null,
    "boughtDate": "16 Mar 2021",
    "zonedBoughtDate": null,
    "reviewStatus": "approved",
    "qcTag": null,
    "qcScore": null,
    "isQced": false,
    "itemId": 171160358,
    "itemPic": "https://static-01.daraz.pk/p/a769833298a7eabb9b49689c3dadb286.jpg",
    "itemTitle": "BEBEM - Pack of 3 Baby diapers - Jumbo economy pack - Size 6 XXL - 44 Pcs ( 16+ kg ).",
    "itemUrl": "https://www.daraz.pk/bebem-pack-of-3-baby-diapers-jumbo-economy-pack-size-6-xxl-44-pcs-16-kg-i171160358-s1341700713.html",
    "originPrice": null,
    "salesPrice": null,
    "promotion": null,
    "skuInfo": "Size Diaper:XXL Size (14-25kg), Diaper Pack Size:44",
    "tags": null,
    "skuId": "1341700713",
    "configSku": "171160358_PK",
    "lastReviewer": "Farooq, ArfeenFarooq, Arfeen",
    "isReportable": 0,
    "reportStatus": null,
    "reportDate": null,
    "reportTimes": 0,
    "upVotes": 0,
    "downVotes": 0,
    "isExternal": 0,
    "replies": [],
    "canEdit": true,
    "images": null,
    "imageQCStatus": null,
    "submitInfo": {
      "os": "ios",
      "source": "myreview",
      "terminal": "msite",
      "network": "4G"
    },
    "imageHost": "//sg-live.slatic.net",
    "showUploader": true,
    "showVideoUploader": false,
    "relevanceScore": 33.63,
    "isCompleted": 1,
    "videoId": null,
    "isVideoReady": null,
    "videoCoverUrl": null,
    "avatar": null,
    "canDownloadImage": null,
    "targetId": 171160358,
    "targetType": "item"
  }
]