[
  {
    "reviewRateId": 17168287416681,
    "reviewType": "PRODUCT_REVIEW",
    "buyerId": 600043929077,
    "buyerName": "3***1",
    "buyerEmail": null,
    "realBuyerName": null,
    "isAnonymous": false,
    "tradeOrderId": null,
    "source": null,
    "clientType": "androidApp",
    "rating": 5,
    "originalRating": null,
    "reviewTitle": null,
    "reviewContent": "wawoooo i really like it thanks daraz thanks to seller i just love it..\ud83e\udd70\ud83e\udd70\ud83e\udd70\ud83e\udd70\ud83e\udd70",
    "reviewTime": "28 May 2021",
    "zonedReviewTime": null,
    "likeCount": 0,
    "likeText": null,
    "isMeLike": null,
    "helpful": true,
    "rejected": false,
    "rejectionReason": null,
    "resubmissionTooltip": null,
    "resubmissionMessage": null,
    "qcReasonId": null,
    "qcDate": null,
    "isPurchased": true,
    "isGuest": false,
    "sellerId": 6005012514058,
    "sellerName": null,
    "boughtDate": "21 May 2021",
    "zonedBoughtDate": null,
    "reviewStatus": "approved",
    "qcTag": null,
    "qcScore": null,
    "isQced": false,
    "itemId": 203716681,
    "itemPic": "https://static-01.daraz.pk/p/06a2bec72e197635b8e33d8a63713d30.jpg",
    "itemTitle": "Baby Bath Mug Cartoon baby shower cap baby shampoo cup child bathing baby bath spoon child shampoo cup child bath baby bath shower mug green/pink",
    "itemUrl": "https://www.daraz.pk/baby-bath-mug-cartoon-baby-shower-cap-baby-shampoo-cup-child-bathing-baby-bath-spoon-child-shampoo-cup-child-bath-baby-bath-shower-mug-greenpink-i203716681-s1427082776.html",
    "originPrice": null,
    "salesPrice": null,
    "promotion": null,
    "skuInfo": "Color Family:Elephant mug pink",
    "tags": null,
    "skuId": "1427082776",
    "configSku": "203716681_PK",
    "lastReviewer": "Farooq, ArfeenFarooq, Arfeen",
    "isReportable": 0,
    "reportStatus": null,
    "reportDate": null,
    "reportTimes": 0,
    "upVotes": 0,
    "downVotes": 0,
    "isExternal": 0,
    "replies": [],
    "canEdit": true,
    "images": [
      {
        "title": "",
        "url": "https://sg-test-11.slatic.net/other/roc/6827d0fb04be6ba8c379d94761a246f4.jpg",
        "sort": 1,
        "uploadTime": 1622226479671,
        "legal": true,
        "status": "approved",
        "checkedByPeople": false,
        "width": 707,
        "height": 906,
        "size": 224844
      }
    ],
    "imageQCStatus": "approved",
    "submitInfo": {
      "os": "ios",
      "source": "order_detail",
      "terminal": "weex",
      "network": "WIFI"
    },
    "imageHost": "//sg-live.slatic.net",
    "showUploader": true,
    "showVideoUploader": false,
    "relevanceScore": 56.08,
    "isCompleted": 1,
    "videoId": null,
    "isVideoReady": null,
    "videoCoverUrl": null,
    "avatar": null,
    "canDownloadImage": null,
    "targetId": 203716681,
    "targetType": "item"
  },
  {
    "reviewRateId": 15642877816681,
    "reviewType": "PRODUCT_REVIEW",
    "buyerId": 2409668,
    "buyerName": "Ayesha J.",
    "buyerEmail": null,
    "realBuyerName": null,
    "isAnonymous": false,
    "tradeOrderId": null,
    "source": null,
    "clientType": "androidApp",
    "rating": 3,
    "originalRating": null,
    "reviewTitle": null,
    "reviewContent": "Green colour Ka kaha tha bt pink send Kar deya",
    "reviewTime": "09 Apr 2021",
    "zonedReviewTime": null,
    "likeCount": 0,
    "likeText": null,
    "isMeLike": null,
    "helpful": true,
    "rejected": false,
    "rejectionReason": null,
    "resubmissionTooltip": null,
    "resubmissionMessage": null,
    "qcReasonId": null,
    "qcDate": null,
    "isPurchased": true,
    "isGuest": false,
    "sellerId": 6005012514058,
    "sellerName": null,
    "boughtDate": "02 Apr 2021",
    "zonedBoughtDate": null,
    "reviewStatus": "approved",
    "qcTag": null,
    "qcScore": null,
    "isQced": false,
    "itemId": 203716681,
    "itemPic": "https://static-01.daraz.pk/p/0ac0cdb7e57a7e117bebe14c3e8a1796.jpg",
    "itemTitle": "Baby Bath Mug Cartoon baby shower cap baby shampoo cup child bathing baby bath spoon child shampoo cup child bath baby bath shower mug green/pink",
    "itemUrl": "https://www.daraz.pk/baby-bath-mug-cartoon-baby-shower-cap-baby-shampoo-cup-child-bathing-baby-bath-spoon-child-shampoo-cup-child-bath-baby-bath-shower-mug-greenpink-i203716681-s1403908179.html",
    "originPrice": null,
    "salesPrice": null,
    "promotion": null,
    "skuInfo": "Color Family:Multi",
    "tags": null,
    "skuId": "1403908179",
    "configSku": "203716681_PK",
    "lastReviewer": "Khan, AyeshaKhan, Ayesha",
    "isReportable": 0,
    "reportStatus": null,
    "reportDate": null,
    "reportTimes": 0,
    "upVotes": 0,
    "downVotes": 0,
    "isExternal": 0,
    "replies": [
      {
        "reviewRateId": 15738269116681,
        "reviewTime": "8  months ago",
        "reviewContent": "apne select pink kra tha ap apni invoicw check kre\nThank you so much for your feedback ?? Follow us to get massive discounts and vouchers. #FollowUs #GetDiscounts #GetVouchers #HappyShopping",
        "reviewerName": "Ayesha J.",
        "reviewerBadge": null,
        "isFollowUp": false,
        "isMeLike": null,
        "likeCount": 0,
        "helpful": null,
        "canReply": false,
        "rejected": false,
        "rejectionReason": null,
        "resubmissionTooltip": null,
        "resubmissionMessage": null,
        "reviewStatus": "approved"
      }
    ],
    "canEdit": true,
    "images": [
      {
        "title": "",
        "url": "https://sg-test-11.slatic.net/other/roc/e706af3e7bc485e2db610364b18669c5.jpg",
        "sort": 1,
        "uploadTime": 1617945360576,
        "legal": true,
        "status": "approved",
        "checkedByPeople": false,
        "width": 1575,
        "height": 2493,
        "size": 987194
      },
      {
        "title": "",
        "url": "https://sg-test-11.slatic.net/other/roc/e4fd0a1f028729149c945aa7f1a89971.jpg",
        "sort": 2,
        "uploadTime": 1617945360576,
        "legal": true,
        "status": "approved",
        "checkedByPeople": false,
        "width": 1827,
        "height": 2609,
        "size": 811157
      }
    ],
    "imageQCStatus": "approved",
    "submitInfo": {
      "os": "ios",
      "source": "myreview",
      "terminal": "weex",
      "network": "WIFI"
    },
    "imageHost": "//sg-live.slatic.net",
    "showUploader": true,
    "showVideoUploader": false,
    "relevanceScore": 55.95,
    "isCompleted": 1,
    "videoId": null,
    "isVideoReady": null,
    "videoCoverUrl": null,
    "avatar": "https://lh3.googleusercontent.com/-f1Xw2VmS1Hk/AAAAAAAAAAI/AAAAAAAAAAA/AAKWJJMnigfDYIK9cnx1ytX8Cmy-lsrIcg/s96-c/photo.jpg",
    "canDownloadImage": null,
    "targetId": 203716681,
    "targetType": "item"
  },
  {
    "reviewRateId": 15591439916681,
    "reviewType": "PRODUCT_REVIEW",
    "buyerId": 600023214870,
    "buyerName": "Aisha M.",
    "buyerEmail": null,
    "realBuyerName": null,
    "isAnonymous": false,
    "tradeOrderId": null,
    "source": null,
    "clientType": "iosApp",
    "rating": 5,
    "originalRating": null,
    "reviewTitle": null,
    "reviewContent": "Good quality like it",
    "reviewTime": "12 Apr 2021",
    "zonedReviewTime": null,
    "likeCount": 0,
    "likeText": null,
    "isMeLike": null,
    "helpful": true,
    "rejected": false,
    "rejectionReason": null,
    "resubmissionTooltip": null,
    "resubmissionMessage": null,
    "qcReasonId": null,
    "qcDate": null,
    "isPurchased": true,
    "isGuest": false,
    "sellerId": 6005012514058,
    "sellerName": null,
    "boughtDate": "04 Apr 2021",
    "zonedBoughtDate": null,
    "reviewStatus": "approved",
    "qcTag": null,
    "qcScore": null,
    "isQced": false,
    "itemId": 203716681,
    "itemPic": "https://static-01.daraz.pk/p/0f02625c41ebcd3d6e00aa0e805369ac.jpg",
    "itemTitle": "Baby Bath Mug Cartoon baby shower cap baby shampoo cup child bathing baby bath spoon child shampoo cup child bath baby bath shower mug green/pink",
    "itemUrl": "https://www.daraz.pk/baby-bath-mug-cartoon-baby-shower-cap-baby-shampoo-cup-child-bathing-baby-bath-spoon-child-shampoo-cup-child-bath-baby-bath-shower-mug-greenpink-i203716681-s1421402157.html",
    "originPrice": null,
    "salesPrice": null,
    "promotion": null,
    "skuInfo": "Color Family:Pink",
    "tags": null,
    "skuId": "1421402157",
    "configSku": "203716681_PK",
    "lastReviewer": "Iqbal, Muhammad AhmedIqbal, Muhammad Ahmed",
    "isReportable": 0,
    "reportStatus": null,
    "reportDate": null,
    "reportTimes": 0,
    "upVotes": 0,
    "downVotes": 0,
    "isExternal": 0,
    "replies": [
      {
        "reviewRateId": 15780201016681,
        "reviewTime": "8  months ago",
        "reviewContent": "Thank you so much for your feedback ?? Follow us to get massive discounts and vouchers. #FollowUs #GetDiscounts #GetVouchers #HappyShopping",
        "reviewerName": "Aisha M.",
        "reviewerBadge": null,
        "isFollowUp": false,
        "isMeLike": null,
        "likeCount": 0,
        "helpful": null,
        "canReply": false,
        "rejected": false,
        "rejectionReason": null,
        "resubmissionTooltip": null,
        "resubmissionMessage": null,
        "reviewStatus": "approved"
      }
    ],
    "canEdit": true,
    "images": [
      {
        "title": "",
        "url": "https://sg-test-11.slatic.net/other/roc/b7071ea2f69ecb8b97a0c0fe6d3719f9.jpg",
        "sort": 1,
        "uploadTime": 1618168198645,
        "legal": true,
        "status": "approved",
        "checkedByPeople": false,
        "width": 2048,
        "height": 2731,
        "size": 330433
      }
    ],
    "imageQCStatus": "approved",
    "submitInfo": {
      "os": "ios",
      "source": "myreview",
      "terminal": "weex",
      "network": "WIFI"
    },
    "imageHost": "//sg-live.slatic.net",
    "showUploader": true,
    "showVideoUploader": false,
    "relevanceScore": 51.5,
    "isCompleted": 1,
    "videoId": null,
    "isVideoReady": null,
    "videoCoverUrl": null,
    "avatar": null,
    "canDownloadImage": null,
    "targetId": 203716681,
    "targetType": "item"
  },
  {
    "reviewRateId": 15515836516681,
    "reviewType": "PRODUCT_REVIEW",
    "buyerId": 600000670274,
    "buyerName": "Saba T.",
    "buyerEmail": null,
    "realBuyerName": null,
    "isAnonymous": false,
    "tradeOrderId": null,
    "source": null,
    "clientType": "androidApp",
    "rating": 5,
    "originalRating": null,
    "reviewTitle": null,
    "reviewContent": "Good quality product ... Got the same colour as ordered ... thanks , Highly recommended !!!\n",
    "reviewTime": "16 Apr 2021",
    "zonedReviewTime": null,
    "likeCount": 0,
    "likeText": null,
    "isMeLike": null,
    "helpful": true,
    "rejected": false,
    "rejectionReason": null,
    "resubmissionTooltip": null,
    "resubmissionMessage": null,
    "qcReasonId": null,
    "qcDate": null,
    "isPurchased": true,
    "isGuest": false,
    "sellerId": 6005012514058,
    "sellerName": null,
    "boughtDate": "30 Mar 2021",
    "zonedBoughtDate": null,
    "reviewStatus": "approved",
    "qcTag": null,
    "qcScore": null,
    "isQced": false,
    "itemId": 203716681,
    "itemPic": "https://static-01.daraz.pk/p/0ac0cdb7e57a7e117bebe14c3e8a1796.jpg",
    "itemTitle": "Baby Bath Mug Cartoon baby shower cap baby shampoo cup child bathing baby bath spoon child shampoo cup child bath baby bath shower mug green/pink",
    "itemUrl": "https://www.daraz.pk/baby-bath-mug-cartoon-baby-shower-cap-baby-shampoo-cup-child-bathing-baby-bath-spoon-child-shampoo-cup-child-bath-baby-bath-shower-mug-greenpink-i203716681-s1403908179.html",
    "originPrice": null,
    "salesPrice": null,
    "promotion": null,
    "skuInfo": "Color Family:Multi",
    "tags": null,
    "skuId": "1403908179",
    "configSku": "203716681_PK",
    "lastReviewer": "Khan, AyeshaKhan, Ayesha",
    "isReportable": 0,
    "reportStatus": null,
    "reportDate": null,
    "reportTimes": 0,
    "upVotes": 0,
    "downVotes": 0,
    "isExternal": 0,
    "replies": [
      {
        "reviewRateId": 15936855516681,
        "reviewTime": "8  months ago",
        "reviewContent": "Thank you so much for your feedback ?? Follow us to get massive discounts and vouchers. #FollowUs #GetDiscounts #GetVouchers #HappyShopping",
        "reviewerName": "Saba T.",
        "reviewerBadge": null,
        "isFollowUp": false,
        "isMeLike": null,
        "likeCount": 0,
        "helpful": null,
        "canReply": false,
        "rejected": false,
        "rejectionReason": null,
        "resubmissionTooltip": null,
        "resubmissionMessage": null,
        "reviewStatus": "approved"
      }
    ],
    "canEdit": true,
    "images": null,
    "imageQCStatus": null,
    "submitInfo": {
      "os": "ios",
      "source": "myreview",
      "terminal": "msite",
      "network": "4G"
    },
    "imageHost": "//sg-live.slatic.net",
    "showUploader": true,
    "showVideoUploader": false,
    "relevanceScore": 39.4,
    "isCompleted": 1,
    "videoId": null,
    "isVideoReady": null,
    "videoCoverUrl": null,
    "avatar": null,
    "canDownloadImage": null,
    "targetId": 203716681,
    "targetType": "item"
  },
  {
    "reviewRateId": 16413015116681,
    "reviewType": "PRODUCT_REVIEW",
    "buyerId": 600018828655,
    "buyerName": "Basharat H.",
    "buyerEmail": null,
    "realBuyerName": null,
    "isAnonymous": false,
    "tradeOrderId": null,
    "source": null,
    "clientType": "androidApp",
    "rating": 2,
    "originalRating": null,
    "reviewTitle": null,
    "reviewContent": "Huge difference in shown picture and physical,  received timely but quality is poor , ",
    "reviewTime": "08 May 2021",
    "zonedReviewTime": null,
    "likeCount": 0,
    "likeText": null,
    "isMeLike": null,
    "helpful": true,
    "rejected": false,
    "rejectionReason": null,
    "resubmissionTooltip": null,
    "resubmissionMessage": null,
    "qcReasonId": null,
    "qcDate": null,
    "isPurchased": true,
    "isGuest": false,
    "sellerId": 6005012514058,
    "sellerName": null,
    "boughtDate": "28 Apr 2021",
    "zonedBoughtDate": null,
    "reviewStatus": "approved",
    "qcTag": null,
    "qcScore": null,
    "isQced": false,
    "itemId": 203716681,
    "itemPic": "https://static-01.daraz.pk/p/0f02625c41ebcd3d6e00aa0e805369ac.jpg",
    "itemTitle": "Baby Bath Mug Cartoon baby shower cap baby shampoo cup child bathing baby bath spoon child shampoo cup child bath baby bath shower mug green/pink",
    "itemUrl": "https://www.daraz.pk/baby-bath-mug-cartoon-baby-shower-cap-baby-shampoo-cup-child-bathing-baby-bath-spoon-child-shampoo-cup-child-bath-baby-bath-shower-mug-greenpink-i203716681-s1421402157.html",
    "originPrice": null,
    "salesPrice": null,
    "promotion": null,
    "skuInfo": "Color Family:Pink",
    "tags": null,
    "skuId": "1421402157",
    "configSku": "203716681_PK",
    "lastReviewer": "Naveed Malik, MustafaNaveed Malik, Mustafa",
    "isReportable": 0,
    "reportStatus": null,
    "reportDate": null,
    "reportTimes": 0,
    "upVotes": 0,
    "downVotes": 0,
    "isExternal": 0,
    "replies": [],
    "canEdit": true,
    "images": null,
    "imageQCStatus": null,
    "submitInfo": {
      "os": "ios",
      "source": "order_detail",
      "terminal": "weex",
      "network": "4G"
    },
    "imageHost": "//sg-live.slatic.net",
    "showUploader": true,
    "showVideoUploader": false,
    "relevanceScore": 38.95,
    "isCompleted": 1,
    "videoId": null,
    "isVideoReady": null,
    "videoCoverUrl": null,
    "avatar": null,
    "canDownloadImage": null,
    "targetId": 203716681,
    "targetType": "item"
  },
  {
    "reviewRateId": 17676443216681,
    "reviewType": "PRODUCT_REVIEW",
    "buyerId": 600008958452,
    "buyerName": "Hina M.",
    "buyerEmail": null,
    "realBuyerName": null,
    "isAnonymous": false,
    "tradeOrderId": null,
    "source": null,
    "clientType": "androidApp",
    "rating": 2,
    "originalRating": null,
    "reviewTitle": null,
    "reviewContent": "Its cut but  too small  and it contains very low water. Waste of money y  ",
    "reviewTime": "17 Jun 2021",
    "zonedReviewTime": null,
    "likeCount": 0,
    "likeText": null,
    "isMeLike": null,
    "helpful": true,
    "rejected": false,
    "rejectionReason": null,
    "resubmissionTooltip": null,
    "resubmissionMessage": null,
    "qcReasonId": null,
    "qcDate": null,
    "isPurchased": true,
    "isGuest": false,
    "sellerId": 6005012514058,
    "sellerName": null,
    "boughtDate": "08 Jun 2021",
    "zonedBoughtDate": null,
    "reviewStatus": "approved",
    "qcTag": null,
    "qcScore": null,
    "isQced": false,
    "itemId": 203716681,
    "itemPic": "https://static-01.daraz.pk/p/ce063f2fc2b4c932e086bacf27d6ccf5.jpg",
    "itemTitle": "Baby Bath Mug Cartoon baby shower cap baby shampoo cup child bathing baby bath spoon child shampoo cup child bath baby bath shower mug green/pink",
    "itemUrl": "https://www.daraz.pk/baby-bath-mug-cartoon-baby-shower-cap-baby-shampoo-cup-child-bathing-baby-bath-spoon-child-shampoo-cup-child-bath-baby-bath-shower-mug-greenpink-i203716681-s1427082775.html",
    "originPrice": null,
    "salesPrice": null,
    "promotion": null,
    "skuInfo": "Color Family:Elephant mug",
    "tags": null,
    "skuId": "1427082775",
    "configSku": "203716681_PK",
    "lastReviewer": "Khan, AyeshaKhan, Ayesha",
    "isReportable": 0,
    "reportStatus": null,
    "reportDate": null,
    "reportTimes": 0,
    "upVotes": 0,
    "downVotes": 0,
    "isExternal": 0,
    "replies": [],
    "canEdit": true,
    "images": null,
    "imageQCStatus": null,
    "submitInfo": {
      "os": "ios",
      "source": "myreview",
      "terminal": "msite",
      "network": "4G"
    },
    "imageHost": "//sg-live.slatic.net",
    "showUploader": true,
    "showVideoUploader": false,
    "relevanceScore": 38.05,
    "isCompleted": 1,
    "videoId": null,
    "isVideoReady": null,
    "videoCoverUrl": null,
    "avatar": "https://static-01.daraz.pk/p/f00764604db315d6261a042b4a5bb531.jpg",
    "canDownloadImage": null,
    "targetId": 203716681,
    "targetType": "item"
  },
  {
    "reviewRateId": 15567678616681,
    "reviewType": "PRODUCT_REVIEW",
    "buyerId": 600017712001,
    "buyerName": "Ambreen S.",
    "buyerEmail": null,
    "realBuyerName": null,
    "isAnonymous": false,
    "tradeOrderId": null,
    "source": null,
    "clientType": "iosApp",
    "rating": 5,
    "originalRating": null,
    "reviewTitle": null,
    "reviewContent": "Received the same as shown in the pic. Good quality mug. Thankyou seller",
    "reviewTime": "06 Apr 2021",
    "zonedReviewTime": null,
    "likeCount": 0,
    "likeText": null,
    "isMeLike": null,
    "helpful": true,
    "rejected": false,
    "rejectionReason": null,
    "resubmissionTooltip": null,
    "resubmissionMessage": null,
    "qcReasonId": null,
    "qcDate": null,
    "isPurchased": true,
    "isGuest": false,
    "sellerId": 6005012514058,
    "sellerName": null,
    "boughtDate": "02 Apr 2021",
    "zonedBoughtDate": null,
    "reviewStatus": "approved",
    "qcTag": null,
    "qcScore": null,
    "isQced": false,
    "itemId": 203716681,
    "itemPic": "https://static-01.daraz.pk/p/0ac0cdb7e57a7e117bebe14c3e8a1796.jpg",
    "itemTitle": "Baby Bath Mug Cartoon baby shower cap baby shampoo cup child bathing baby bath spoon child shampoo cup child bath baby bath shower mug green/pink",
    "itemUrl": "https://www.daraz.pk/baby-bath-mug-cartoon-baby-shower-cap-baby-shampoo-cup-child-bathing-baby-bath-spoon-child-shampoo-cup-child-bath-baby-bath-shower-mug-greenpink-i203716681-s1403908179.html",
    "originPrice": null,
    "salesPrice": null,
    "promotion": null,
    "skuInfo": "Color Family:Multi",
    "tags": null,
    "skuId": "1403908179",
    "configSku": "203716681_PK",
    "lastReviewer": "Khan, AyeshaKhan, Ayesha",
    "isReportable": 0,
    "reportStatus": null,
    "reportDate": null,
    "reportTimes": 0,
    "upVotes": 0,
    "downVotes": 0,
    "isExternal": 0,
    "replies": [
      {
        "reviewRateId": 15627618016681,
        "reviewTime": "8  months ago",
        "reviewContent": "Thank you so much for your feedback ?? Follow us to get massive discounts and vouchers. #FollowUs #GetDiscounts #GetVouchers #HappyShopping",
        "reviewerName": "Ambreen S.",
        "reviewerBadge": null,
        "isFollowUp": false,
        "isMeLike": null,
        "likeCount": 0,
        "helpful": null,
        "canReply": false,
        "rejected": false,
        "rejectionReason": null,
        "resubmissionTooltip": null,
        "resubmissionMessage": null,
        "reviewStatus": "approved"
      }
    ],
    "canEdit": true,
    "images": null,
    "imageQCStatus": null,
    "submitInfo": {
      "os": "ios",
      "source": "order_detail",
      "terminal": "weex",
      "network": "WIFI"
    },
    "imageHost": "//sg-live.slatic.net",
    "showUploader": true,
    "showVideoUploader": false,
    "relevanceScore": 37.9,
    "isCompleted": 1,
    "videoId": null,
    "isVideoReady": null,
    "videoCoverUrl": null,
    "avatar": null,
    "canDownloadImage": null,
    "targetId": 203716681,
    "targetType": "item"
  },
  {
    "reviewRateId": 15077682916681,
    "reviewType": "PRODUCT_REVIEW",
    "buyerId": 600029334794,
    "buyerName": "3***3",
    "buyerEmail": null,
    "realBuyerName": null,
    "isAnonymous": false,
    "tradeOrderId": null,
    "source": null,
    "clientType": "androidApp",
    "rating": 5,
    "originalRating": null,
    "reviewTitle": null,
    "reviewContent": "Wonderful quality and very attractive for baby. ",
    "reviewTime": "30 Mar 2021",
    "zonedReviewTime": null,
    "likeCount": 0,
    "likeText": null,
    "isMeLike": null,
    "helpful": true,
    "rejected": false,
    "rejectionReason": null,
    "resubmissionTooltip": null,
    "resubmissionMessage": null,
    "qcReasonId": null,
    "qcDate": null,
    "isPurchased": true,
    "isGuest": false,
    "sellerId": 6005012514058,
    "sellerName": null,
    "boughtDate": "20 Mar 2021",
    "zonedBoughtDate": null,
    "reviewStatus": "approved",
    "qcTag": null,
    "qcScore": null,
    "isQced": false,
    "itemId": 203716681,
    "itemPic": "https://static-01.daraz.pk/p/0ac0cdb7e57a7e117bebe14c3e8a1796.jpg",
    "itemTitle": "Baby Bath Mug Cartoon baby shower cap baby shampoo cup child bathing baby bath spoon child shampoo cup child bath baby bath shower mug green/pink",
    "itemUrl": "https://www.daraz.pk/baby-bath-mug-cartoon-baby-shower-cap-baby-shampoo-cup-child-bathing-baby-bath-spoon-child-shampoo-cup-child-bath-baby-bath-shower-mug-greenpink-i203716681-s1403908179.html",
    "originPrice": null,
    "salesPrice": null,
    "promotion": null,
    "skuInfo": "Color Family:Multi",
    "tags": null,
    "skuId": "1403908179",
    "configSku": "203716681_PK",
    "lastReviewer": "Khan, AyeshaKhan, Ayesha",
    "isReportable": 0,
    "reportStatus": null,
    "reportDate": null,
    "reportTimes": 0,
    "upVotes": 0,
    "downVotes": 0,
    "isExternal": 0,
    "replies": [
      {
        "reviewRateId": 15429058116681,
        "reviewTime": "8  months ago",
        "reviewContent": "Thank you so much for your feedback ?? Follow us to get massive discounts and vouchers. #FollowUs #GetDiscounts #GetVouchers #HappyShopping",
        "reviewerName": "3***3",
        "reviewerBadge": null,
        "isFollowUp": false,
        "isMeLike": null,
        "likeCount": 0,
        "helpful": null,
        "canReply": false,
        "rejected": false,
        "rejectionReason": null,
        "resubmissionTooltip": null,
        "resubmissionMessage": null,
        "reviewStatus": "approved"
      }
    ],
    "canEdit": true,
    "images": null,
    "imageQCStatus": null,
    "submitInfo": {
      "os": "ios",
      "source": "myreview",
      "terminal": "weex",
      "network": "4G"
    },
    "imageHost": "//sg-live.slatic.net",
    "showUploader": true,
    "showVideoUploader": false,
    "relevanceScore": 36.1,
    "isCompleted": 1,
    "videoId": null,
    "isVideoReady": null,
    "videoCoverUrl": null,
    "avatar": null,
    "canDownloadImage": null,
    "targetId": 203716681,
    "targetType": "item"
  },
  {
    "reviewRateId": 16747067316681,
    "reviewType": "PRODUCT_REVIEW",
    "buyerId": 600011607389,
    "buyerName": "Yousra K.",
    "buyerEmail": null,
    "realBuyerName": null,
    "isAnonymous": false,
    "tradeOrderId": null,
    "source": null,
    "clientType": "androidApp",
    "rating": 5,
    "originalRating": null,
    "reviewTitle": null,
    "reviewContent": "good quality baby enjoy it thanks for this \u263a\ufe0f",
    "reviewTime": "18 May 2021",
    "zonedReviewTime": null,
    "likeCount": 0,
    "likeText": null,
    "isMeLike": null,
    "helpful": true,
    "rejected": false,
    "rejectionReason": null,
    "resubmissionTooltip": null,
    "resubmissionMessage": null,
    "qcReasonId": null,
    "qcDate": null,
    "isPurchased": true,
    "isGuest": false,
    "sellerId": 6005012514058,
    "sellerName": null,
    "boughtDate": "16 May 2021",
    "zonedBoughtDate": null,
    "reviewStatus": "approved",
    "qcTag": null,
    "qcScore": null,
    "isQced": true,
    "itemId": 203716681,
    "itemPic": "https://static-01.daraz.pk/p/ce063f2fc2b4c932e086bacf27d6ccf5.jpg",
    "itemTitle": "Baby Bath Mug Cartoon baby shower cap baby shampoo cup child bathing baby bath spoon child shampoo cup child bath baby bath shower mug green/pink",
    "itemUrl": "https://www.daraz.pk/baby-bath-mug-cartoon-baby-shower-cap-baby-shampoo-cup-child-bathing-baby-bath-spoon-child-shampoo-cup-child-bath-baby-bath-shower-mug-greenpink-i203716681-s1427082775.html",
    "originPrice": null,
    "salesPrice": null,
    "promotion": null,
    "skuInfo": "Color Family:Elephant mug",
    "tags": null,
    "skuId": "1427082775",
    "configSku": "203716681_PK",
    "lastReviewer": "csi",
    "isReportable": 0,
    "reportStatus": null,
    "reportDate": null,
    "reportTimes": 0,
    "upVotes": 0,
    "downVotes": 0,
    "isExternal": 0,
    "replies": [],
    "canEdit": true,
    "images": null,
    "imageQCStatus": null,
    "submitInfo": {
      "os": "ios",
      "source": "myreview",
      "terminal": "weex",
      "network": "WIFI"
    },
    "imageHost": "//sg-live.slatic.net",
    "showUploader": true,
    "showVideoUploader": false,
    "relevanceScore": 35.88,
    "isCompleted": 1,
    "videoId": null,
    "isVideoReady": null,
    "videoCoverUrl": null,
    "avatar": "https://graph.facebook.com/2494356897514541/picture",
    "canDownloadImage": null,
    "targetId": 203716681,
    "targetType": "item"
  },
  {
    "reviewRateId": 18106248116681,
    "reviewType": "PRODUCT_REVIEW",
    "buyerId": 600045654819,
    "buyerName": "3***2",
    "buyerEmail": null,
    "realBuyerName": null,
    "isAnonymous": false,
    "tradeOrderId": null,
    "source": null,
    "clientType": "androidApp",
    "rating": 5,
    "originalRating": null,
    "reviewTitle": null,
    "reviewContent": "mug size to much small",
    "reviewTime": "27 Jun 2021",
    "zonedReviewTime": null,
    "likeCount": 0,
    "likeText": null,
    "isMeLike": null,
    "helpful": true,
    "rejected": false,
    "rejectionReason": null,
    "resubmissionTooltip": null,
    "resubmissionMessage": null,
    "qcReasonId": null,
    "qcDate": null,
    "isPurchased": true,
    "isGuest": false,
    "sellerId": 6005012514058,
    "sellerName": null,
    "boughtDate": "23 Jun 2021",
    "zonedBoughtDate": null,
    "reviewStatus": "approved",
    "qcTag": null,
    "qcScore": null,
    "isQced": false,
    "itemId": 203716681,
    "itemPic": "https://static-01.daraz.pk/p/08b625982c80e366896acd6482d5777c.jpg",
    "itemTitle": "Baby Bath Mug Cartoon baby shower cap baby shampoo cup child bathing baby bath spoon child shampoo cup child bath baby bath shower mug green/pink",
    "itemUrl": "https://www.daraz.pk/baby-bath-mug-cartoon-baby-shower-cap-baby-shampoo-cup-child-bathing-baby-bath-spoon-child-shampoo-cup-child-bath-baby-bath-shower-mug-greenpink-i203716681-s1427082777.html",
    "originPrice": null,
    "salesPrice": null,
    "promotion": null,
    "skuInfo": "Color Family:Elephant mug blue",
    "tags": null,
    "skuId": "1427082777",
    "configSku": "203716681_PK",
    "lastReviewer": "Khan, AyeshaKhan, Ayesha",
    "isReportable": 0,
    "reportStatus": null,
    "reportDate": null,
    "reportTimes": 0,
    "upVotes": 0,
    "downVotes": 0,
    "isExternal": 0,
    "replies": [],
    "canEdit": true,
    "images": null,
    "imageQCStatus": null,
    "submitInfo": {
      "os": "ios",
      "source": "order_detail",
      "terminal": "weex",
      "network": "WIFI"
    },
    "imageHost": "//sg-live.slatic.net",
    "showUploader": true,
    "showVideoUploader": false,
    "relevanceScore": 34.15,
    "isCompleted": 1,
    "videoId": null,
    "isVideoReady": null,
    "videoCoverUrl": null,
    "avatar": null,
    "canDownloadImage": null,
    "targetId": 203716681,
    "targetType": "item"
  },
  {
    "reviewRateId": 15995696616681,
    "reviewType": "PRODUCT_REVIEW",
    "buyerId": 971966,
    "buyerName": "Xohaib A.",
    "buyerEmail": null,
    "realBuyerName": null,
    "isAnonymous": false,
    "tradeOrderId": null,
    "source": null,
    "clientType": "iosApp",
    "rating": 5,
    "originalRating": null,
    "reviewTitle": null,
    "reviewContent": "Very suitable for kids",
    "reviewTime": "21 Apr 2021",
    "zonedReviewTime": null,
    "likeCount": 0,
    "likeText": null,
    "isMeLike": null,
    "helpful": true,
    "rejected": false,
    "rejectionReason": null,
    "resubmissionTooltip": null,
    "resubmissionMessage": null,
    "qcReasonId": null,
    "qcDate": null,
    "isPurchased": true,
    "isGuest": false,
    "sellerId": 6005012514058,
    "sellerName": null,
    "boughtDate": "15 Apr 2021",
    "zonedBoughtDate": null,
    "reviewStatus": "approved",
    "qcTag": null,
    "qcScore": null,
    "isQced": false,
    "itemId": 203716681,
    "itemPic": "https://static-01.daraz.pk/p/0f02625c41ebcd3d6e00aa0e805369ac.jpg",
    "itemTitle": "Baby Bath Mug Cartoon baby shower cap baby shampoo cup child bathing baby bath spoon child shampoo cup child bath baby bath shower mug green/pink",
    "itemUrl": "https://www.daraz.pk/baby-bath-mug-cartoon-baby-shower-cap-baby-shampoo-cup-child-bathing-baby-bath-spoon-child-shampoo-cup-child-bath-baby-bath-shower-mug-greenpink-i203716681-s1421402157.html",
    "originPrice": null,
    "salesPrice": null,
    "promotion": null,
    "skuInfo": "Color Family:Pink",
    "tags": null,
    "skuId": "1421402157",
    "configSku": "203716681_PK",
    "lastReviewer": "Naveed Malik, MustafaNaveed Malik, Mustafa",
    "isReportable": 0,
    "reportStatus": null,
    "reportDate": null,
    "reportTimes": 0,
    "upVotes": 0,
    "downVotes": 0,
    "isExternal": 0,
    "replies": [
      {
        "reviewRateId": 16025633916681,
        "reviewTime": "8  months ago",
        "reviewContent": "Thank you so much for your feedback ?? Follow us to get massive discounts and vouchers. #FollowUs #GetDiscounts #GetVouchers #HappyShopping",
        "reviewerName": "Xohaib A.",
        "reviewerBadge": null,
        "isFollowUp": false,
        "isMeLike": null,
        "likeCount": 0,
        "helpful": null,
        "canReply": false,
        "rejected": false,
        "rejectionReason": null,
        "resubmissionTooltip": null,
        "resubmissionMessage": null,
        "reviewStatus": "approved"
      }
    ],
    "canEdit": true,
    "images": null,
    "imageQCStatus": null,
    "submitInfo": {
      "os": "ios",
      "source": "myreview",
      "terminal": "weex",
      "network": "WIFI"
    },
    "imageHost": "//sg-live.slatic.net",
    "showUploader": true,
    "showVideoUploader": false,
    "relevanceScore": 34.15,
    "isCompleted": 1,
    "videoId": null,
    "isVideoReady": null,
    "videoCoverUrl": null,
    "avatar": "https://graph.facebook.com/10213888323341753/picture",
    "canDownloadImage": null,
    "targetId": 203716681,
    "targetType": "item"
  },
  {
    "reviewRateId": 15298877416681,
    "reviewType": "PRODUCT_REVIEW",
    "buyerId": 600028413335,
    "buyerName": "3***1",
    "buyerEmail": null,
    "realBuyerName": null,
    "isAnonymous": false,
    "tradeOrderId": null,
    "source": null,
    "clientType": "androidApp",
    "rating": 5,
    "originalRating": null,
    "reviewTitle": null,
    "reviewContent": "god quality plastic",
    "reviewTime": "29 Mar 2021",
    "zonedReviewTime": null,
    "likeCount": 0,
    "likeText": null,
    "isMeLike": null,
    "helpful": true,
    "rejected": false,
    "rejectionReason": null,
    "resubmissionTooltip": null,
    "resubmissionMessage": null,
    "qcReasonId": null,
    "qcDate": null,
    "isPurchased": true,
    "isGuest": false,
    "sellerId": 6005012514058,
    "sellerName": null,
    "boughtDate": "25 Mar 2021",
    "zonedBoughtDate": null,
    "reviewStatus": "approved",
    "qcTag": null,
    "qcScore": null,
    "isQced": false,
    "itemId": 203716681,
    "itemPic": "https://static-01.daraz.pk/p/0ac0cdb7e57a7e117bebe14c3e8a1796.jpg",
    "itemTitle": "Baby Bath Mug Cartoon baby shower cap baby shampoo cup child bathing baby bath spoon child shampoo cup child bath baby bath shower mug green/pink",
    "itemUrl": "https://www.daraz.pk/baby-bath-mug-cartoon-baby-shower-cap-baby-shampoo-cup-child-bathing-baby-bath-spoon-child-shampoo-cup-child-bath-baby-bath-shower-mug-greenpink-i203716681-s1403908179.html",
    "originPrice": null,
    "salesPrice": null,
    "promotion": null,
    "skuInfo": "Color Family:Multi",
    "tags": null,
    "skuId": "1403908179",
    "configSku": "203716681_PK",
    "lastReviewer": "Khan, AyeshaKhan, Ayesha",
    "isReportable": 0,
    "reportStatus": null,
    "reportDate": null,
    "reportTimes": 0,
    "upVotes": 0,
    "downVotes": 0,
    "isExternal": 0,
    "replies": [
      {
        "reviewRateId": 15394659816681,
        "reviewTime": "9  months ago",
        "reviewContent": "Thank you so much for your feedback ?? Follow us to get massive discounts and vouchers. #FollowUs #GetDiscounts #GetVouchers #HappyShopping",
        "reviewerName": "3***1",
        "reviewerBadge": null,
        "isFollowUp": false,
        "isMeLike": null,
        "likeCount": 0,
        "helpful": null,
        "canReply": false,
        "rejected": false,
        "rejectionReason": null,
        "resubmissionTooltip": null,
        "resubmissionMessage": null,
        "reviewStatus": "approved"
      }
    ],
    "canEdit": true,
    "images": null,
    "imageQCStatus": null,
    "submitInfo": {
      "os": "ios",
      "source": "myreview",
      "terminal": "weex",
      "network": "WIFI"
    },
    "imageHost": "//sg-live.slatic.net",
    "showUploader": true,
    "showVideoUploader": false,
    "relevanceScore": 33.93,
    "isCompleted": 1,
    "videoId": null,
    "isVideoReady": null,
    "videoCoverUrl": null,
    "avatar": null,
    "canDownloadImage": null,
    "targetId": 203716681,
    "targetType": "item"
  },
  {
    "reviewRateId": 15894090816681,
    "reviewType": "PRODUCT_REVIEW",
    "buyerId": 600041295528,
    "buyerName": "0***0",
    "buyerEmail": null,
    "realBuyerName": null,
    "isAnonymous": false,
    "tradeOrderId": null,
    "source": null,
    "clientType": "androidApp",
    "rating": 5,
    "originalRating": null,
    "reviewTitle": null,
    "reviewContent": "Amazing thanks \u263a\ufe0f",
    "reviewTime": "29 Apr 2021",
    "zonedReviewTime": null,
    "likeCount": 0,
    "likeText": null,
    "isMeLike": null,
    "helpful": true,
    "rejected": false,
    "rejectionReason": null,
    "resubmissionTooltip": null,
    "resubmissionMessage": null,
    "qcReasonId": null,
    "qcDate": null,
    "isPurchased": true,
    "isGuest": false,
    "sellerId": 6005012514058,
    "sellerName": null,
    "boughtDate": "13 Apr 2021",
    "zonedBoughtDate": null,
    "reviewStatus": "approved",
    "qcTag": null,
    "qcScore": null,
    "isQced": false,
    "itemId": 203716681,
    "itemPic": "https://static-01.daraz.pk/p/0ac0cdb7e57a7e117bebe14c3e8a1796.jpg",
    "itemTitle": "Baby Bath Mug Cartoon baby shower cap baby shampoo cup child bathing baby bath spoon child shampoo cup child bath baby bath shower mug green/pink",
    "itemUrl": "https://www.daraz.pk/baby-bath-mug-cartoon-baby-shower-cap-baby-shampoo-cup-child-bathing-baby-bath-spoon-child-shampoo-cup-child-bath-baby-bath-shower-mug-greenpink-i203716681-s1403908179.html",
    "originPrice": null,
    "salesPrice": null,
    "promotion": null,
    "skuInfo": "Color Family:Multi",
    "tags": null,
    "skuId": "1403908179",
    "configSku": "203716681_PK",
    "lastReviewer": "Khan, AyeshaKhan, Ayesha",
    "isReportable": 0,
    "reportStatus": null,
    "reportDate": null,
    "reportTimes": 0,
    "upVotes": 0,
    "downVotes": 0,
    "isExternal": 0,
    "replies": [
      {
        "reviewRateId": 16291677616681,
        "reviewTime": "7  months ago",
        "reviewContent": "Thank you so much for your feedback ?? Follow us to get massive discounts and vouchers. #FollowUs #GetDiscounts #GetVouchers #HappyShopping",
        "reviewerName": "0***0",
        "reviewerBadge": null,
        "isFollowUp": false,
        "isMeLike": null,
        "likeCount": 0,
        "helpful": null,
        "canReply": false,
        "rejected": false,
        "rejectionReason": null,
        "resubmissionTooltip": null,
        "resubmissionMessage": null,
        "reviewStatus": "approved"
      }
    ],
    "canEdit": true,
    "images": null,
    "imageQCStatus": null,
    "submitInfo": {
      "os": "ios",
      "source": "myreview",
      "terminal": "weex",
      "network": "3G"
    },
    "imageHost": "//sg-live.slatic.net",
    "showUploader": true,
    "showVideoUploader": false,
    "relevanceScore": 33.78,
    "isCompleted": 1,
    "videoId": null,
    "isVideoReady": null,
    "videoCoverUrl": null,
    "avatar": null,
    "canDownloadImage": null,
    "targetId": 203716681,
    "targetType": "item"
  }
]